[
  {
    "timestamp": "2026-01-20T07:31:29.000Z",
    "PM1": 6.6,
    "PM2.5": 7,
    "PM4": 7,
    "PM10": 7,
    "HUM1": 40.17,
    "TMP1": 19.44,
    "VOC": 167,
    "NOX": 1,
    "CO2": 494,
    "HUM2": 38.38,
    "TMP2": 19.35,
    "HUM": 40.43,
    "TMP": 19.14
  },
  {
    "timestamp": "2026-01-20T07:31:57.000Z",
    "PM1": 6.7,
    "PM2.5": 7.1,
    "PM4": 7.1,
    "PM10": 7.1,
    "HUM1": 40.15,
    "TMP1": 19.44,
    "VOC": 166,
    "NOX": 1,
    "CO2": 493,
    "HUM2": 38.41,
    "TMP2": 19.35,
    "HUM": 40.43,
    "TMP": 19.15
  },
  {
    "timestamp": "2026-01-20T07:32:27.000Z",
    "PM1": 6.7,
    "PM2.5": 7,
    "PM4": 7,
    "PM10": 7,
    "HUM1": 40.11,
    "TMP1": 19.44,
    "VOC": 166,
    "NOX": 1,
    "CO2": 492,
    "HUM2": 38.39,
    "TMP2": 19.32,
    "HUM": 40.38,
    "TMP": 19.15
  },
  {
    "timestamp": "2026-01-20T07:32:57.000Z",
    "PM1": 5.7,
    "PM2.5": 6,
    "PM4": 6,
    "PM10": 6,
    "HUM1": 40.1,
    "TMP1": 19.44,
    "VOC": 164,
    "NOX": 1,
    "CO2": 492,
    "HUM2": 38.4,
    "TMP2": 19.34,
    "HUM": 40.44,
    "TMP": 19.13
  },
  {
    "timestamp": "2026-01-20T07:33:27.000Z",
    "PM1": 6.1,
    "PM2.5": 6.4,
    "PM4": 6.4,
    "PM10": 6.4,
    "HUM1": 40.14,
    "TMP1": 19.44,
    "VOC": 164,
    "NOX": 1,
    "CO2": 492,
    "HUM2": 38.42,
    "TMP2": 19.32,
    "HUM": 40.39,
    "TMP": 19.13
  },
  {
    "timestamp": "2026-01-20T07:33:57.000Z",
    "PM1": 5.6,
    "PM2.5": 5.9,
    "PM4": 5.9,
    "PM10": 5.9,
    "HUM1": 40.2,
    "TMP1": 19.43,
    "VOC": 163,
    "NOX": 1,
    "CO2": 492,
    "HUM2": 38.38,
    "TMP2": 19.31,
    "HUM": 40.4,
    "TMP": 19.15
  },
  {
    "timestamp": "2026-01-20T07:34:27.000Z",
    "PM1": 6.1,
    "PM2.5": 6.4,
    "PM4": 6.4,
    "PM10": 6.4,
    "HUM1": 40.15,
    "TMP1": 19.43,
    "VOC": 162,
    "NOX": 1,
    "CO2": 494,
    "HUM2": 38.35,
    "TMP2": 19.33,
    "HUM": 40.35,
    "TMP": 19.13
  },
  {
    "timestamp": "2026-01-20T07:34:57.000Z",
    "PM1": 5.9,
    "PM2.5": 6.2,
    "PM4": 6.2,
    "PM10": 6.2,
    "HUM1": 40.14,
    "TMP1": 19.43,
    "VOC": 162,
    "NOX": 1,
    "CO2": 494,
    "HUM2": 38.37,
    "TMP2": 19.31,
    "HUM": 40.39,
    "TMP": 19.13
  },
  {
    "timestamp": "2026-01-20T07:35:27.000Z",
    "PM1": 6,
    "PM2.5": 6.3,
    "PM4": 6.3,
    "PM10": 6.3,
    "HUM1": 40.08,
    "TMP1": 19.43,
    "VOC": 160,
    "NOX": 1,
    "CO2": 493,
    "HUM2": 38.39,
    "TMP2": 19.29,
    "HUM": 40.38,
    "TMP": 19.11
  },
  {
    "timestamp": "2026-01-20T07:35:57.000Z",
    "PM1": 5.7,
    "PM2.5": 6,
    "PM4": 6,
    "PM10": 6,
    "HUM1": 40.09,
    "TMP1": 19.43,
    "VOC": 158,
    "NOX": 1,
    "CO2": 492,
    "HUM2": 38.33,
    "TMP2": 19.29,
    "HUM": 40.39,
    "TMP": 19.13
  },
  {
    "timestamp": "2026-01-20T07:36:27.000Z",
    "PM1": 5.5,
    "PM2.5": 5.7,
    "PM4": 5.7,
    "PM10": 5.7,
    "HUM1": 40.07,
    "TMP1": 19.43,
    "VOC": 157,
    "NOX": 1,
    "CO2": 490,
    "HUM2": 38.36,
    "TMP2": 19.31,
    "HUM": 40.35,
    "TMP": 19.1
  },
  {
    "timestamp": "2026-01-20T07:36:57.000Z",
    "PM1": 6.5,
    "PM2.5": 6.8,
    "PM4": 6.8,
    "PM10": 6.8,
    "HUM1": 40.11,
    "TMP1": 19.43,
    "VOC": 157,
    "NOX": 1,
    "CO2": 491,
    "HUM2": 38.4,
    "TMP2": 19.3,
    "HUM": 40.38,
    "TMP": 19.11
  },
  {
    "timestamp": "2026-01-20T07:37:27.000Z",
    "PM1": 6.4,
    "PM2.5": 6.7,
    "PM4": 6.7,
    "PM10": 6.7,
    "HUM1": 40.17,
    "TMP1": 19.43,
    "VOC": 157,
    "NOX": 1,
    "CO2": 488,
    "HUM2": 38.39,
    "TMP2": 19.29,
    "HUM": 40.39,
    "TMP": 19.11
  },
  {
    "timestamp": "2026-01-20T07:37:57.000Z",
    "PM1": 5.9,
    "PM2.5": 6.2,
    "PM4": 6.2,
    "PM10": 6.2,
    "HUM1": 40.12,
    "TMP1": 19.43,
    "VOC": 157,
    "NOX": 1,
    "CO2": 487,
    "HUM2": 38.39,
    "TMP2": 19.3,
    "HUM": 40.41,
    "TMP": 19.13
  },
  {
    "timestamp": "2026-01-20T07:38:27.000Z",
    "PM1": 6.1,
    "PM2.5": 6.4,
    "PM4": 6.4,
    "PM10": 6.4,
    "HUM1": 40.13,
    "TMP1": 19.43,
    "VOC": 157,
    "NOX": 1,
    "CO2": 485,
    "HUM2": 38.44,
    "TMP2": 19.29,
    "HUM": 40.4,
    "TMP": 19.1
  },
  {
    "timestamp": "2026-01-20T07:38:57.000Z",
    "PM1": 5.3,
    "PM2.5": 5.5,
    "PM4": 5.5,
    "PM10": 5.5,
    "HUM1": 40.11,
    "TMP1": 19.43,
    "VOC": 156,
    "NOX": 1,
    "CO2": 486,
    "HUM2": 38.44,
    "TMP2": 19.29,
    "HUM": 40.42,
    "TMP": 19.11
  },
  {
    "timestamp": "2026-01-20T07:39:27.000Z",
    "PM1": 6,
    "PM2.5": 6.2,
    "PM4": 6.2,
    "PM10": 6.2,
    "HUM1": 40.1,
    "TMP1": 19.43,
    "VOC": 155,
    "NOX": 1,
    "CO2": 486,
    "HUM2": 38.37,
    "TMP2": 19.29,
    "HUM": 40.4,
    "TMP": 19.11
  },
  {
    "timestamp": "2026-01-20T07:39:57.000Z",
    "PM1": 6.6,
    "PM2.5": 6.9,
    "PM4": 6.9,
    "PM10": 6.9,
    "HUM1": 40.12,
    "TMP1": 19.43,
    "VOC": 154,
    "NOX": 1,
    "CO2": 485,
    "HUM2": 38.38,
    "TMP2": 19.32,
    "HUM": 40.42,
    "TMP": 19.1
  },
  {
    "timestamp": "2026-01-20T07:40:27.000Z",
    "PM1": 6.4,
    "PM2.5": 6.8,
    "PM4": 6.8,
    "PM10": 6.8,
    "HUM1": 40.15,
    "TMP1": 19.43,
    "VOC": 154,
    "NOX": 1,
    "CO2": 486,
    "HUM2": 38.44,
    "TMP2": 19.29,
    "HUM": 40.39,
    "TMP": 19.13
  },
  {
    "timestamp": "2026-01-20T07:40:57.000Z",
    "PM1": 5.7,
    "PM2.5": 6,
    "PM4": 6,
    "PM10": 6,
    "HUM1": 40.19,
    "TMP1": 19.42,
    "VOC": 154,
    "NOX": 1,
    "CO2": 485,
    "HUM2": 38.42,
    "TMP2": 19.3,
    "HUM": 40.49,
    "TMP": 19.12
  },
  {
    "timestamp": "2026-01-20T07:41:27.000Z",
    "PM1": 6.2,
    "PM2.5": 6.5,
    "PM4": 6.5,
    "PM10": 6.5,
    "HUM1": 40.17,
    "TMP1": 19.42,
    "VOC": 153,
    "NOX": 1,
    "CO2": 484,
    "HUM2": 38.38,
    "TMP2": 19.28,
    "HUM": 40.44,
    "TMP": 19.11
  },
  {
    "timestamp": "2026-01-20T07:41:57.000Z",
    "PM1": 5.6,
    "PM2.5": 5.9,
    "PM4": 5.9,
    "PM10": 5.9,
    "HUM1": 40.12,
    "TMP1": 19.42,
    "VOC": 154,
    "NOX": 1,
    "CO2": 483,
    "HUM2": 38.39,
    "TMP2": 19.31,
    "HUM": 40.43,
    "TMP": 19.1
  },
  {
    "timestamp": "2026-01-20T07:42:27.000Z",
    "PM1": 5.9,
    "PM2.5": 6.2,
    "PM4": 6.2,
    "PM10": 6.2,
    "HUM1": 40.18,
    "TMP1": 19.42,
    "VOC": 154,
    "NOX": 1,
    "CO2": 483,
    "HUM2": 38.44,
    "TMP2": 19.27,
    "HUM": 40.44,
    "TMP": 19.11
  },
  {
    "timestamp": "2026-01-20T07:42:57.000Z",
    "PM1": 5.8,
    "PM2.5": 6,
    "PM4": 6,
    "PM10": 6,
    "HUM1": 40.2,
    "TMP1": 19.42,
    "VOC": 153,
    "NOX": 1,
    "CO2": 484,
    "HUM2": 38.43,
    "TMP2": 19.29,
    "HUM": 40.42,
    "TMP": 19.09
  },
  {
    "timestamp": "2026-01-20T07:43:27.000Z",
    "PM1": 5.3,
    "PM2.5": 5.5,
    "PM4": 5.5,
    "PM10": 5.5,
    "HUM1": 40.19,
    "TMP1": 19.42,
    "VOC": 153,
    "NOX": 1,
    "CO2": 482,
    "HUM2": 38.42,
    "TMP2": 19.27,
    "HUM": 40.41,
    "TMP": 19.13
  },
  {
    "timestamp": "2026-01-20T07:43:57.000Z",
    "PM1": 6.2,
    "PM2.5": 6.6,
    "PM4": 6.6,
    "PM10": 6.6,
    "HUM1": 40.23,
    "TMP1": 19.42,
    "VOC": 153,
    "NOX": 1,
    "CO2": 482,
    "HUM2": 38.41,
    "TMP2": 19.28,
    "HUM": 40.45,
    "TMP": 19.11
  },
  {
    "timestamp": "2026-01-20T07:44:27.000Z",
    "PM1": 5.9,
    "PM2.5": 6.2,
    "PM4": 6.2,
    "PM10": 6.2,
    "HUM1": 40.22,
    "TMP1": 19.42,
    "VOC": 154,
    "NOX": 1,
    "CO2": 483,
    "HUM2": 38.41,
    "TMP2": 19.29,
    "HUM": 40.45,
    "TMP": 19.1
  },
  {
    "timestamp": "2026-01-20T07:44:57.000Z",
    "PM1": 5.7,
    "PM2.5": 5.9,
    "PM4": 5.9,
    "PM10": 5.9,
    "HUM1": 40.29,
    "TMP1": 19.42,
    "VOC": 155,
    "NOX": 1,
    "CO2": 483,
    "HUM2": 38.48,
    "TMP2": 19.29,
    "HUM": 40.5,
    "TMP": 19.08
  },
  {
    "timestamp": "2026-01-20T07:45:27.000Z",
    "PM1": 5.8,
    "PM2.5": 6.1,
    "PM4": 6.1,
    "PM10": 6.1,
    "HUM1": 40.26,
    "TMP1": 19.42,
    "VOC": 157,
    "NOX": 1,
    "CO2": 484,
    "HUM2": 38.46,
    "TMP2": 19.27,
    "HUM": 40.49,
    "TMP": 19.1
  },
  {
    "timestamp": "2026-01-20T07:45:57.000Z",
    "PM1": 6.2,
    "PM2.5": 6.5,
    "PM4": 6.5,
    "PM10": 6.5,
    "HUM1": 40.25,
    "TMP1": 19.41,
    "VOC": 158,
    "NOX": 1,
    "CO2": 484,
    "HUM2": 38.48,
    "TMP2": 19.28,
    "HUM": 40.53,
    "TMP": 19.07
  },
  {
    "timestamp": "2026-01-20T07:46:27.000Z",
    "PM1": 5.9,
    "PM2.5": 6.2,
    "PM4": 6.2,
    "PM10": 6.2,
    "HUM1": 40.29,
    "TMP1": 19.41,
    "VOC": 158,
    "NOX": 1,
    "CO2": 484,
    "HUM2": 38.5,
    "TMP2": 19.3,
    "HUM": 40.54,
    "TMP": 19.09
  },
  {
    "timestamp": "2026-01-20T07:46:57.000Z",
    "PM1": 6.1,
    "PM2.5": 6.3,
    "PM4": 6.3,
    "PM10": 6.3,
    "HUM1": 40.34,
    "TMP1": 19.4,
    "VOC": 158,
    "NOX": 1,
    "CO2": 484,
    "HUM2": 38.54,
    "TMP2": 19.26,
    "HUM": 40.52,
    "TMP": 19.09
  },
  {
    "timestamp": "2026-01-20T07:47:27.000Z",
    "PM1": 5.6,
    "PM2.5": 5.8,
    "PM4": 5.8,
    "PM10": 5.8,
    "HUM1": 40.32,
    "TMP1": 19.4,
    "VOC": 158,
    "NOX": 1,
    "CO2": 486,
    "HUM2": 38.55,
    "TMP2": 19.28,
    "HUM": 40.55,
    "TMP": 19.09
  },
  {
    "timestamp": "2026-01-20T07:47:57.000Z",
    "PM1": 6.1,
    "PM2.5": 6.4,
    "PM4": 6.4,
    "PM10": 6.4,
    "HUM1": 40.35,
    "TMP1": 19.4,
    "VOC": 159,
    "NOX": 1,
    "CO2": 485,
    "HUM2": 38.49,
    "TMP2": 19.3,
    "HUM": 40.58,
    "TMP": 19.11
  },
  {
    "timestamp": "2026-01-20T07:48:27.000Z",
    "PM1": 5.6,
    "PM2.5": 5.8,
    "PM4": 5.8,
    "PM10": 5.8,
    "HUM1": 40.38,
    "TMP1": 19.4,
    "VOC": 160,
    "NOX": 1,
    "CO2": 486,
    "HUM2": 38.57,
    "TMP2": 19.28,
    "HUM": 40.56,
    "TMP": 19.1
  },
  {
    "timestamp": "2026-01-20T07:48:57.000Z",
    "PM1": 5.9,
    "PM2.5": 6.2,
    "PM4": 6.2,
    "PM10": 6.2,
    "HUM1": 40.4,
    "TMP1": 19.4,
    "VOC": 160,
    "NOX": 1,
    "CO2": 487,
    "HUM2": 38.55,
    "TMP2": 19.28,
    "HUM": 40.61,
    "TMP": 19.09
  },
  {
    "timestamp": "2026-01-20T07:49:27.000Z",
    "PM1": 6.1,
    "PM2.5": 6.4,
    "PM4": 6.4,
    "PM10": 6.4,
    "HUM1": 40.42,
    "TMP1": 19.39,
    "VOC": 162,
    "NOX": 1,
    "CO2": 488,
    "HUM2": 38.58,
    "TMP2": 19.26,
    "HUM": 40.61,
    "TMP": 19.09
  },
  {
    "timestamp": "2026-01-20T07:49:57.000Z",
    "PM1": 6.4,
    "PM2.5": 6.7,
    "PM4": 6.7,
    "PM10": 6.7,
    "HUM1": 40.4,
    "TMP1": 19.39,
    "VOC": 163,
    "NOX": 1,
    "CO2": 489,
    "HUM2": 38.57,
    "TMP2": 19.28,
    "HUM": 40.58,
    "TMP": 19.09
  },
  {
    "timestamp": "2026-01-20T07:50:27.000Z",
    "PM1": 6.1,
    "PM2.5": 6.4,
    "PM4": 6.4,
    "PM10": 6.4,
    "HUM1": 40.4,
    "TMP1": 19.39,
    "VOC": 163,
    "NOX": 1,
    "CO2": 489,
    "HUM2": 38.57,
    "TMP2": 19.28,
    "HUM": 40.57,
    "TMP": 19.07
  },
  {
    "timestamp": "2026-01-20T07:50:57.000Z",
    "PM1": 5.5,
    "PM2.5": 5.8,
    "PM4": 5.8,
    "PM10": 5.8,
    "HUM1": 40.41,
    "TMP1": 19.39,
    "VOC": 165,
    "NOX": 1,
    "CO2": 489,
    "HUM2": 38.6,
    "TMP2": 19.26,
    "HUM": 40.6,
    "TMP": 19.1
  },
  {
    "timestamp": "2026-01-20T07:51:27.000Z",
    "PM1": 5.9,
    "PM2.5": 6.1,
    "PM4": 6.1,
    "PM10": 6.1,
    "HUM1": 40.36,
    "TMP1": 19.39,
    "VOC": 165,
    "NOX": 1,
    "CO2": 488,
    "HUM2": 38.61,
    "TMP2": 19.27,
    "HUM": 40.58,
    "TMP": 19.08
  },
  {
    "timestamp": "2026-01-20T07:51:57.000Z",
    "PM1": 6.2,
    "PM2.5": 6.5,
    "PM4": 6.5,
    "PM10": 6.5,
    "HUM1": 40.35,
    "TMP1": 19.39,
    "VOC": 166,
    "NOX": 1,
    "CO2": 488,
    "HUM2": 38.55,
    "TMP2": 19.27,
    "HUM": 40.59,
    "TMP": 19.07
  },
  {
    "timestamp": "2026-01-20T07:52:27.000Z",
    "PM1": 5.9,
    "PM2.5": 6.2,
    "PM4": 6.2,
    "PM10": 6.2,
    "HUM1": 40.36,
    "TMP1": 19.39,
    "VOC": 166,
    "NOX": 1,
    "CO2": 487,
    "HUM2": 38.55,
    "TMP2": 19.28,
    "HUM": 40.58,
    "TMP": 19.1
  },
  {
    "timestamp": "2026-01-20T07:52:57.000Z",
    "PM1": 5.3,
    "PM2.5": 5.6,
    "PM4": 5.6,
    "PM10": 5.6,
    "HUM1": 40.37,
    "TMP1": 19.39,
    "VOC": 166,
    "NOX": 1,
    "CO2": 486,
    "HUM2": 38.54,
    "TMP2": 19.27,
    "HUM": 40.56,
    "TMP": 19.09
  },
  {
    "timestamp": "2026-01-20T07:53:27.000Z",
    "PM1": 4.8,
    "PM2.5": 5.1,
    "PM4": 5.1,
    "PM10": 5.1,
    "HUM1": 40.37,
    "TMP1": 19.38,
    "VOC": 166,
    "NOX": 1,
    "CO2": 484,
    "HUM2": 38.56,
    "TMP2": 19.25,
    "HUM": 40.6,
    "TMP": 19.07
  },
  {
    "timestamp": "2026-01-20T07:53:57.000Z",
    "PM1": 5.5,
    "PM2.5": 5.7,
    "PM4": 5.7,
    "PM10": 5.7,
    "HUM1": 40.38,
    "TMP1": 19.38,
    "VOC": 166,
    "NOX": 1,
    "CO2": 483,
    "HUM2": 38.55,
    "TMP2": 19.27,
    "HUM": 40.55,
    "TMP": 19.1
  },
  {
    "timestamp": "2026-01-20T07:54:27.000Z",
    "PM1": 6.4,
    "PM2.5": 6.7,
    "PM4": 6.7,
    "PM10": 6.7,
    "HUM1": 40.4,
    "TMP1": 19.37,
    "VOC": 165,
    "NOX": 1,
    "CO2": 482,
    "HUM2": 38.58,
    "TMP2": 19.26,
    "HUM": 40.58,
    "TMP": 19.09
  },
  {
    "timestamp": "2026-01-20T07:54:57.000Z",
    "PM1": 5.7,
    "PM2.5": 5.9,
    "PM4": 5.9,
    "PM10": 5.9,
    "HUM1": 40.42,
    "TMP1": 19.36,
    "VOC": 168,
    "NOX": 1,
    "CO2": 482,
    "HUM2": 38.6,
    "TMP2": 19.27,
    "HUM": 40.65,
    "TMP": 19.08
  },
  {
    "timestamp": "2026-01-20T07:55:27.000Z",
    "PM1": 5.6,
    "PM2.5": 5.9,
    "PM4": 5.9,
    "PM10": 5.9,
    "HUM1": 40.46,
    "TMP1": 19.36,
    "VOC": 168,
    "NOX": 1,
    "CO2": 483,
    "HUM2": 38.55,
    "TMP2": 19.26,
    "HUM": 40.65,
    "TMP": 19.08
  },
  {
    "timestamp": "2026-01-20T07:55:57.000Z",
    "PM1": 5.7,
    "PM2.5": 6,
    "PM4": 6,
    "PM10": 6,
    "HUM1": 40.44,
    "TMP1": 19.36,
    "VOC": 168,
    "NOX": 1,
    "CO2": 484,
    "HUM2": 38.57,
    "TMP2": 19.26,
    "HUM": 40.64,
    "TMP": 19.08
  },
  {
    "timestamp": "2026-01-20T07:56:27.000Z",
    "PM1": 5.9,
    "PM2.5": 6.2,
    "PM4": 6.2,
    "PM10": 6.2,
    "HUM1": 40.43,
    "TMP1": 19.36,
    "VOC": 167,
    "NOX": 1,
    "CO2": 484,
    "HUM2": 38.57,
    "TMP2": 19.27,
    "HUM": 40.62,
    "TMP": 19.09
  },
  {
    "timestamp": "2026-01-20T07:56:57.000Z",
    "PM1": 5.5,
    "PM2.5": 5.7,
    "PM4": 5.7,
    "PM10": 5.7,
    "HUM1": 40.44,
    "TMP1": 19.36,
    "VOC": 167,
    "NOX": 1,
    "CO2": 483,
    "HUM2": 38.58,
    "TMP2": 19.26,
    "HUM": 40.62,
    "TMP": 19.09
  },
  {
    "timestamp": "2026-01-20T07:57:27.000Z",
    "PM1": 5.8,
    "PM2.5": 6.1,
    "PM4": 6.1,
    "PM10": 6.1,
    "HUM1": 40.48,
    "TMP1": 19.35,
    "VOC": 167,
    "NOX": 1,
    "CO2": 484,
    "HUM2": 38.58,
    "TMP2": 19.26,
    "HUM": 40.61,
    "TMP": 19.07
  },
  {
    "timestamp": "2026-01-20T07:57:57.000Z",
    "PM1": 5.4,
    "PM2.5": 5.6,
    "PM4": 5.6,
    "PM10": 5.6,
    "HUM1": 40.51,
    "TMP1": 19.35,
    "VOC": 167,
    "NOX": 1,
    "CO2": 482,
    "HUM2": 38.6,
    "TMP2": 19.26,
    "HUM": 40.62,
    "TMP": 19.06
  },
  {
    "timestamp": "2026-01-20T07:58:27.000Z",
    "PM1": 5.8,
    "PM2.5": 6.1,
    "PM4": 6.1,
    "PM10": 6.1,
    "HUM1": 40.54,
    "TMP1": 19.35,
    "VOC": 167,
    "NOX": 1,
    "CO2": 482,
    "HUM2": 38.64,
    "TMP2": 19.26,
    "HUM": 40.64,
    "TMP": 19.07
  },
  {
    "timestamp": "2026-01-20T07:58:57.000Z",
    "PM1": 5.9,
    "PM2.5": 6.2,
    "PM4": 6.2,
    "PM10": 6.2,
    "HUM1": 40.54,
    "TMP1": 19.35,
    "VOC": 168,
    "NOX": 1,
    "CO2": 482,
    "HUM2": 38.6,
    "TMP2": 19.26,
    "HUM": 40.63,
    "TMP": 19.04
  },
  {
    "timestamp": "2026-01-20T07:59:27.000Z",
    "PM1": 5.1,
    "PM2.5": 5.3,
    "PM4": 5.3,
    "PM10": 5.3,
    "HUM1": 40.49,
    "TMP1": 19.35,
    "VOC": 168,
    "NOX": 1,
    "CO2": 483,
    "HUM2": 38.61,
    "TMP2": 19.24,
    "HUM": 40.66,
    "TMP": 19.06
  },
  {
    "timestamp": "2026-01-20T07:59:57.000Z",
    "PM1": 5.9,
    "PM2.5": 6.2,
    "PM4": 6.2,
    "PM10": 6.2,
    "HUM1": 40.44,
    "TMP1": 19.35,
    "VOC": 169,
    "NOX": 1,
    "CO2": 482,
    "HUM2": 38.62,
    "TMP2": 19.26,
    "HUM": 40.63,
    "TMP": 19.07
  },
  {
    "timestamp": "2026-01-20T08:00:27.000Z",
    "PM1": 5.8,
    "PM2.5": 6.1,
    "PM4": 6.1,
    "PM10": 6.1,
    "HUM1": 40.44,
    "TMP1": 19.35,
    "VOC": 169,
    "NOX": 1,
    "CO2": 482,
    "HUM2": 38.63,
    "TMP2": 19.25,
    "HUM": 40.57,
    "TMP": 19.06
  },
  {
    "timestamp": "2026-01-20T08:00:57.000Z",
    "PM1": 5.6,
    "PM2.5": 5.9,
    "PM4": 5.9,
    "PM10": 5.9,
    "HUM1": 40.39,
    "TMP1": 19.35,
    "VOC": 169,
    "NOX": 1,
    "CO2": 481,
    "HUM2": 38.65,
    "TMP2": 19.27,
    "HUM": 40.59,
    "TMP": 19.05
  },
  {
    "timestamp": "2026-01-20T08:01:27.000Z",
    "PM1": 5.7,
    "PM2.5": 6,
    "PM4": 6,
    "PM10": 6.1,
    "HUM1": 40.4,
    "TMP1": 19.35,
    "VOC": 168,
    "NOX": 1,
    "CO2": 482,
    "HUM2": 38.62,
    "TMP2": 19.23,
    "HUM": 40.61,
    "TMP": 19.04
  },
  {
    "timestamp": "2026-01-20T08:01:57.000Z",
    "PM1": 6,
    "PM2.5": 6.2,
    "PM4": 6.2,
    "PM10": 6.2,
    "HUM1": 40.32,
    "TMP1": 19.36,
    "VOC": 168,
    "NOX": 1,
    "CO2": 482,
    "HUM2": 38.63,
    "TMP2": 19.23,
    "HUM": 40.56,
    "TMP": 19.03
  },
  {
    "timestamp": "2026-01-20T08:02:27.000Z",
    "PM1": 5,
    "PM2.5": 5.2,
    "PM4": 5.2,
    "PM10": 5.2,
    "HUM1": 40.25,
    "TMP1": 19.36,
    "VOC": 166,
    "NOX": 1,
    "CO2": 482,
    "HUM2": 38.57,
    "TMP2": 19.24,
    "HUM": 40.54,
    "TMP": 19.05
  },
  {
    "timestamp": "2026-01-20T08:02:57.000Z",
    "PM1": 5,
    "PM2.5": 5.3,
    "PM4": 5.3,
    "PM10": 5.3,
    "HUM1": 40.22,
    "TMP1": 19.35,
    "VOC": 162,
    "NOX": 1,
    "CO2": 480,
    "HUM2": 38.56,
    "TMP2": 19.25,
    "HUM": 40.55,
    "TMP": 19.04
  },
  {
    "timestamp": "2026-01-20T08:03:27.000Z",
    "PM1": 5.8,
    "PM2.5": 6.1,
    "PM4": 6.1,
    "PM10": 6.1,
    "HUM1": 40.23,
    "TMP1": 19.35,
    "VOC": 159,
    "NOX": 1,
    "CO2": 479,
    "HUM2": 38.53,
    "TMP2": 19.23,
    "HUM": 40.5,
    "TMP": 19.05
  },
  {
    "timestamp": "2026-01-20T08:03:57.000Z",
    "PM1": 6,
    "PM2.5": 6.3,
    "PM4": 6.3,
    "PM10": 6.3,
    "HUM1": 40.28,
    "TMP1": 19.35,
    "VOC": 156,
    "NOX": 1,
    "CO2": 478,
    "HUM2": 38.59,
    "TMP2": 19.23,
    "HUM": 40.51,
    "TMP": 19.05
  },
  {
    "timestamp": "2026-01-20T08:04:27.000Z",
    "PM1": 5.9,
    "PM2.5": 6.2,
    "PM4": 6.2,
    "PM10": 6.2,
    "HUM1": 40.26,
    "TMP1": 19.35,
    "VOC": 155,
    "NOX": 1,
    "CO2": 477,
    "HUM2": 38.53,
    "TMP2": 19.21,
    "HUM": 40.55,
    "TMP": 19.06
  },
  {
    "timestamp": "2026-01-20T08:04:57.000Z",
    "PM1": 5.8,
    "PM2.5": 6.1,
    "PM4": 6.1,
    "PM10": 6.1,
    "HUM1": 40.23,
    "TMP1": 19.35,
    "VOC": 154,
    "NOX": 1,
    "CO2": 475,
    "HUM2": 38.55,
    "TMP2": 19.23,
    "HUM": 40.5,
    "TMP": 19.01
  },
  {
    "timestamp": "2026-01-20T08:05:27.000Z",
    "PM1": 5.5,
    "PM2.5": 5.7,
    "PM4": 5.7,
    "PM10": 5.7,
    "HUM1": 40.25,
    "TMP1": 19.34,
    "VOC": 154,
    "NOX": 1,
    "CO2": 475,
    "HUM2": 38.52,
    "TMP2": 19.21,
    "HUM": 40.54,
    "TMP": 19.04
  },
  {
    "timestamp": "2026-01-20T08:05:57.000Z",
    "PM1": 5,
    "PM2.5": 5.2,
    "PM4": 5.2,
    "PM10": 5.2,
    "HUM1": 40.24,
    "TMP1": 19.34,
    "VOC": 153,
    "NOX": 1,
    "CO2": 474,
    "HUM2": 38.55,
    "TMP2": 19.21,
    "HUM": 40.49,
    "TMP": 19.03
  },
  {
    "timestamp": "2026-01-20T08:06:26.000Z",
    "PM1": 4.8,
    "PM2.5": 5.1,
    "PM4": 5.1,
    "PM10": 5.1,
    "HUM1": 40.29,
    "TMP1": 19.34,
    "VOC": 153,
    "NOX": 1,
    "CO2": 474,
    "HUM2": 38.53,
    "TMP2": 19.21,
    "HUM": 40.54,
    "TMP": 19.03
  },
  {
    "timestamp": "2026-01-20T08:06:56.000Z",
    "PM1": 5.3,
    "PM2.5": 5.6,
    "PM4": 5.6,
    "PM10": 5.6,
    "HUM1": 40.35,
    "TMP1": 19.34,
    "VOC": 154,
    "NOX": 1,
    "CO2": 473,
    "HUM2": 38.57,
    "TMP2": 19.2,
    "HUM": 40.56,
    "TMP": 19.04
  },
  {
    "timestamp": "2026-01-20T08:07:26.000Z",
    "PM1": 4.8,
    "PM2.5": 5.1,
    "PM4": 5.1,
    "PM10": 5.1,
    "HUM1": 40.33,
    "TMP1": 19.33,
    "VOC": 155,
    "NOX": 1,
    "CO2": 474,
    "HUM2": 38.59,
    "TMP2": 19.22,
    "HUM": 40.58,
    "TMP": 19.03
  },
  {
    "timestamp": "2026-01-20T08:07:56.000Z",
    "PM1": 5.6,
    "PM2.5": 5.9,
    "PM4": 5.9,
    "PM10": 5.9,
    "HUM1": 40.35,
    "TMP1": 19.33,
    "VOC": 155,
    "NOX": 1,
    "CO2": 473,
    "HUM2": 38.6,
    "TMP2": 19.22,
    "HUM": 40.67,
    "TMP": 19.03
  },
  {
    "timestamp": "2026-01-20T08:08:26.000Z",
    "PM1": 5.4,
    "PM2.5": 5.7,
    "PM4": 5.7,
    "PM10": 5.7,
    "HUM1": 40.39,
    "TMP1": 19.33,
    "VOC": 155,
    "NOX": 1,
    "CO2": 472,
    "HUM2": 38.6,
    "TMP2": 19.2,
    "HUM": 40.59,
    "TMP": 19.02
  },
  {
    "timestamp": "2026-01-20T08:08:56.000Z",
    "PM1": 5.5,
    "PM2.5": 5.8,
    "PM4": 5.8,
    "PM10": 5.8,
    "HUM1": 40.31,
    "TMP1": 19.33,
    "VOC": 155,
    "NOX": 1,
    "CO2": 471,
    "HUM2": 38.62,
    "TMP2": 19.21,
    "HUM": 40.62,
    "TMP": 19.05
  },
  {
    "timestamp": "2026-01-20T08:09:26.000Z",
    "PM1": 5,
    "PM2.5": 5.2,
    "PM4": 5.2,
    "PM10": 5.2,
    "HUM1": 40.36,
    "TMP1": 19.33,
    "VOC": 156,
    "NOX": 1,
    "CO2": 472,
    "HUM2": 38.64,
    "TMP2": 19.22,
    "HUM": 40.54,
    "TMP": 19.02
  },
  {
    "timestamp": "2026-01-20T08:09:56.000Z",
    "PM1": 5.2,
    "PM2.5": 5.5,
    "PM4": 5.5,
    "PM10": 5.5,
    "HUM1": 40.28,
    "TMP1": 19.33,
    "VOC": 156,
    "NOX": 1,
    "CO2": 473,
    "HUM2": 38.56,
    "TMP2": 19.21,
    "HUM": 40.52,
    "TMP": 19.04
  },
  {
    "timestamp": "2026-01-20T08:10:26.000Z",
    "PM1": 5,
    "PM2.5": 5.2,
    "PM4": 5.2,
    "PM10": 5.2,
    "HUM1": 40.26,
    "TMP1": 19.33,
    "VOC": 155,
    "NOX": 1,
    "CO2": 474,
    "HUM2": 38.57,
    "TMP2": 19.2,
    "HUM": 40.54,
    "TMP": 19.02
  },
  {
    "timestamp": "2026-01-20T08:10:56.000Z",
    "PM1": 5.3,
    "PM2.5": 5.6,
    "PM4": 5.6,
    "PM10": 5.6,
    "HUM1": 40.26,
    "TMP1": 19.33,
    "VOC": 155,
    "NOX": 1,
    "CO2": 474,
    "HUM2": 38.55,
    "TMP2": 19.2,
    "HUM": 40.49,
    "TMP": 19.02
  },
  {
    "timestamp": "2026-01-20T08:11:26.000Z",
    "PM1": 5.1,
    "PM2.5": 5.4,
    "PM4": 5.4,
    "PM10": 5.4,
    "HUM1": 40.27,
    "TMP1": 19.33,
    "VOC": 155,
    "NOX": 1,
    "CO2": 474,
    "HUM2": 38.52,
    "TMP2": 19.22,
    "HUM": 40.53,
    "TMP": 19.02
  },
  {
    "timestamp": "2026-01-20T08:11:56.000Z",
    "PM1": 5.1,
    "PM2.5": 5.3,
    "PM4": 5.3,
    "PM10": 5.3,
    "HUM1": 40.26,
    "TMP1": 19.32,
    "VOC": 154,
    "NOX": 1,
    "CO2": 474,
    "HUM2": 38.55,
    "TMP2": 19.22,
    "HUM": 40.52,
    "TMP": 19.03
  },
  {
    "timestamp": "2026-01-20T08:11:56.000Z",
    "PM1": 5.1,
    "PM2.5": 5.3,
    "PM4": 5.3,
    "PM10": 5.3,
    "HUM1": 40.26,
    "TMP1": 19.32,
    "VOC": 154,
    "NOX": 1,
    "CO2": 474,
    "HUM2": 38.55,
    "TMP2": 19.22,
    "HUM": 40.52,
    "TMP": 19.03
  },
  {
    "timestamp": "2026-01-20T08:12:26.000Z",
    "PM1": 4.9,
    "PM2.5": 5.1,
    "PM4": 5.1,
    "PM10": 5.1,
    "HUM1": 40.19,
    "TMP1": 19.32,
    "VOC": 153,
    "NOX": 1,
    "CO2": 472,
    "HUM2": 38.54,
    "TMP2": 19.2,
    "HUM": 40.46,
    "TMP": 19.02
  },
  {
    "timestamp": "2026-01-20T08:12:56.000Z",
    "PM1": 4.5,
    "PM2.5": 4.7,
    "PM4": 4.7,
    "PM10": 4.7,
    "HUM1": 40.12,
    "TMP1": 19.32,
    "VOC": 149,
    "NOX": 1,
    "CO2": 472,
    "HUM2": 38.53,
    "TMP2": 19.21,
    "HUM": 40.52,
    "TMP": 19.01
  },
  {
    "timestamp": "2026-01-20T08:13:26.000Z",
    "PM1": 6.4,
    "PM2.5": 6.7,
    "PM4": 6.7,
    "PM10": 6.7,
    "HUM1": 40.09,
    "TMP1": 19.32,
    "VOC": 147,
    "NOX": 1,
    "CO2": 472,
    "HUM2": 38.53,
    "TMP2": 19.2,
    "HUM": 40.45,
    "TMP": 19.01
  },
  {
    "timestamp": "2026-01-20T08:13:56.000Z",
    "PM1": 5,
    "PM2.5": 5.3,
    "PM4": 5.3,
    "PM10": 5.3,
    "HUM1": 40.17,
    "TMP1": 19.32,
    "VOC": 146,
    "NOX": 1,
    "CO2": 470,
    "HUM2": 38.46,
    "TMP2": 19.22,
    "HUM": 40.41,
    "TMP": 19.01
  },
  {
    "timestamp": "2026-01-20T08:14:26.000Z",
    "PM1": 4.9,
    "PM2.5": 5.2,
    "PM4": 5.2,
    "PM10": 5.2,
    "HUM1": 40.28,
    "TMP1": 19.32,
    "VOC": 146,
    "NOX": 1,
    "CO2": 472,
    "HUM2": 38.55,
    "TMP2": 19.16,
    "HUM": 40.44,
    "TMP": 19.03
  },
  {
    "timestamp": "2026-01-20T08:14:56.000Z",
    "PM1": 5.2,
    "PM2.5": 5.4,
    "PM4": 5.4,
    "PM10": 5.4,
    "HUM1": 40.17,
    "TMP1": 19.31,
    "VOC": 146,
    "NOX": 1,
    "CO2": 472,
    "HUM2": 38.53,
    "TMP2": 19.18,
    "HUM": 40.43,
    "TMP": 19.03
  },
  {
    "timestamp": "2026-01-20T08:15:26.000Z",
    "PM1": 5.4,
    "PM2.5": 5.7,
    "PM4": 5.7,
    "PM10": 5.7,
    "HUM1": 40.15,
    "TMP1": 19.31,
    "VOC": 146,
    "NOX": 1,
    "CO2": 470,
    "HUM2": 38.5,
    "TMP2": 19.21,
    "HUM": 40.45,
    "TMP": 19
  },
  {
    "timestamp": "2026-01-20T08:15:56.000Z",
    "PM1": 5.1,
    "PM2.5": 5.4,
    "PM4": 5.4,
    "PM10": 5.4,
    "HUM1": 40.15,
    "TMP1": 19.31,
    "VOC": 146,
    "NOX": 1,
    "CO2": 471,
    "HUM2": 38.51,
    "TMP2": 19.18,
    "HUM": 40.45,
    "TMP": 19.01
  },
  {
    "timestamp": "2026-01-20T08:16:26.000Z",
    "PM1": 6,
    "PM2.5": 6.3,
    "PM4": 6.3,
    "PM10": 6.3,
    "HUM1": 40.23,
    "TMP1": 19.31,
    "VOC": 147,
    "NOX": 1,
    "CO2": 470,
    "HUM2": 38.52,
    "TMP2": 19.2,
    "HUM": 40.47,
    "TMP": 19.01
  },
  {
    "timestamp": "2026-01-20T08:16:56.000Z",
    "PM1": 5.5,
    "PM2.5": 5.7,
    "PM4": 5.7,
    "PM10": 5.7,
    "HUM1": 40.23,
    "TMP1": 19.3,
    "VOC": 148,
    "NOX": 1,
    "CO2": 471,
    "HUM2": 38.48,
    "TMP2": 19.19,
    "HUM": 40.5,
    "TMP": 19.03
  },
  {
    "timestamp": "2026-01-20T08:17:26.000Z",
    "PM1": 4.6,
    "PM2.5": 4.8,
    "PM4": 4.8,
    "PM10": 4.8,
    "HUM1": 40.24,
    "TMP1": 19.3,
    "VOC": 148,
    "NOX": 1,
    "CO2": 473,
    "HUM2": 38.51,
    "TMP2": 19.19,
    "HUM": 40.47,
    "TMP": 19
  },
  {
    "timestamp": "2026-01-20T08:17:56.000Z",
    "PM1": 4.5,
    "PM2.5": 4.7,
    "PM4": 4.7,
    "PM10": 4.7,
    "HUM1": 40.33,
    "TMP1": 19.3,
    "VOC": 148,
    "NOX": 1,
    "CO2": 472,
    "HUM2": 38.49,
    "TMP2": 19.2,
    "HUM": 40.43,
    "TMP": 19.02
  },
  {
    "timestamp": "2026-01-20T08:18:26.000Z",
    "PM1": 4.9,
    "PM2.5": 5.1,
    "PM4": 5.1,
    "PM10": 5.1,
    "HUM1": 40.38,
    "TMP1": 19.3,
    "VOC": 149,
    "NOX": 1,
    "CO2": 472,
    "HUM2": 38.48,
    "TMP2": 19.18,
    "HUM": 40.4,
    "TMP": 19
  },
  {
    "timestamp": "2026-01-20T08:18:56.000Z",
    "PM1": 4.4,
    "PM2.5": 4.6,
    "PM4": 4.6,
    "PM10": 4.6,
    "HUM1": 40.27,
    "TMP1": 19.3,
    "VOC": 149,
    "NOX": 1,
    "CO2": 472,
    "HUM2": 38.47,
    "TMP2": 19.17,
    "HUM": 40.45,
    "TMP": 18.99
  },
  {
    "timestamp": "2026-01-20T08:19:26.000Z",
    "PM1": 5.1,
    "PM2.5": 5.3,
    "PM4": 5.3,
    "PM10": 5.3,
    "HUM1": 40.26,
    "TMP1": 19.3,
    "VOC": 150,
    "NOX": 1,
    "CO2": 471,
    "HUM2": 38.5,
    "TMP2": 19.22,
    "HUM": 40.47,
    "TMP": 18.99
  },
  {
    "timestamp": "2026-01-20T08:19:56.000Z",
    "PM1": 5.3,
    "PM2.5": 5.6,
    "PM4": 5.6,
    "PM10": 5.6,
    "HUM1": 40.28,
    "TMP1": 19.29,
    "VOC": 151,
    "NOX": 1,
    "CO2": 471,
    "HUM2": 38.5,
    "TMP2": 19.21,
    "HUM": 40.47,
    "TMP": 19.01
  },
  {
    "timestamp": "2026-01-20T08:20:26.000Z",
    "PM1": 5.2,
    "PM2.5": 5.4,
    "PM4": 5.4,
    "PM10": 5.4,
    "HUM1": 40.27,
    "TMP1": 19.29,
    "VOC": 151,
    "NOX": 1,
    "CO2": 471,
    "HUM2": 38.48,
    "TMP2": 19.17,
    "HUM": 40.5,
    "TMP": 19
  },
  {
    "timestamp": "2026-01-20T08:20:56.000Z",
    "PM1": 5,
    "PM2.5": 5.3,
    "PM4": 5.3,
    "PM10": 5.3,
    "HUM1": 40.39,
    "TMP1": 19.28,
    "VOC": 152,
    "NOX": 1,
    "CO2": 471,
    "HUM2": 38.51,
    "TMP2": 19.21,
    "HUM": 40.5,
    "TMP": 19.02
  },
  {
    "timestamp": "2026-01-20T08:21:26.000Z",
    "PM1": 4.4,
    "PM2.5": 4.6,
    "PM4": 4.6,
    "PM10": 4.6,
    "HUM1": 40.44,
    "TMP1": 19.27,
    "VOC": 154,
    "NOX": 1,
    "CO2": 472,
    "HUM2": 38.55,
    "TMP2": 19.18,
    "HUM": 40.53,
    "TMP": 19
  },
  {
    "timestamp": "2026-01-20T08:21:56.000Z",
    "PM1": 4.7,
    "PM2.5": 4.9,
    "PM4": 4.9,
    "PM10": 4.9,
    "HUM1": 40.44,
    "TMP1": 19.27,
    "VOC": 154,
    "NOX": 1,
    "CO2": 472,
    "HUM2": 38.55,
    "TMP2": 19.17,
    "HUM": 40.53,
    "TMP": 19.01
  },
  {
    "timestamp": "2026-01-20T08:22:26.000Z",
    "PM1": 5.1,
    "PM2.5": 5.3,
    "PM4": 5.3,
    "PM10": 5.3,
    "HUM1": 40.45,
    "TMP1": 19.27,
    "VOC": 155,
    "NOX": 1,
    "CO2": 471,
    "HUM2": 38.58,
    "TMP2": 19.19,
    "HUM": 40.54,
    "TMP": 19
  },
  {
    "timestamp": "2026-01-20T08:22:56.000Z",
    "PM1": 5.2,
    "PM2.5": 5.4,
    "PM4": 5.4,
    "PM10": 5.4,
    "HUM1": 40.45,
    "TMP1": 19.27,
    "VOC": 157,
    "NOX": 1,
    "CO2": 471,
    "HUM2": 38.58,
    "TMP2": 19.19,
    "HUM": 40.57,
    "TMP": 19.01
  },
  {
    "timestamp": "2026-01-20T08:23:26.000Z",
    "PM1": 5.2,
    "PM2.5": 5.5,
    "PM4": 5.5,
    "PM10": 5.5,
    "HUM1": 40.45,
    "TMP1": 19.27,
    "VOC": 159,
    "NOX": 1,
    "CO2": 471,
    "HUM2": 38.58,
    "TMP2": 19.18,
    "HUM": 40.59,
    "TMP": 18.99
  },
  {
    "timestamp": "2026-01-20T08:23:56.000Z",
    "PM1": 5,
    "PM2.5": 5.3,
    "PM4": 5.3,
    "PM10": 5.3,
    "HUM1": 40.5,
    "TMP1": 19.27,
    "VOC": 160,
    "NOX": 1,
    "CO2": 471,
    "HUM2": 38.58,
    "TMP2": 19.19,
    "HUM": 40.62,
    "TMP": 19.01
  },
  {
    "timestamp": "2026-01-20T08:24:26.000Z",
    "PM1": 5.1,
    "PM2.5": 5.3,
    "PM4": 5.3,
    "PM10": 5.3,
    "HUM1": 40.49,
    "TMP1": 19.27,
    "VOC": 161,
    "NOX": 1,
    "CO2": 471,
    "HUM2": 38.57,
    "TMP2": 19.19,
    "HUM": 40.64,
    "TMP": 18.99
  },
  {
    "timestamp": "2026-01-20T08:24:56.000Z",
    "PM1": 5.2,
    "PM2.5": 5.4,
    "PM4": 5.4,
    "PM10": 5.4,
    "HUM1": 40.47,
    "TMP1": 19.26,
    "VOC": 161,
    "NOX": 1,
    "CO2": 473,
    "HUM2": 38.6,
    "TMP2": 19.19,
    "HUM": 40.62,
    "TMP": 19
  },
  {
    "timestamp": "2026-01-20T08:25:26.000Z",
    "PM1": 5.3,
    "PM2.5": 5.6,
    "PM4": 5.6,
    "PM10": 5.6,
    "HUM1": 40.44,
    "TMP1": 19.26,
    "VOC": 161,
    "NOX": 1,
    "CO2": 474,
    "HUM2": 38.6,
    "TMP2": 19.19,
    "HUM": 40.64,
    "TMP": 18.99
  },
  {
    "timestamp": "2026-01-20T08:25:56.000Z",
    "PM1": 5.7,
    "PM2.5": 5.9,
    "PM4": 5.9,
    "PM10": 5.9,
    "HUM1": 40.44,
    "TMP1": 19.26,
    "VOC": 162,
    "NOX": 1,
    "CO2": 474,
    "HUM2": 38.68,
    "TMP2": 19.19,
    "HUM": 40.62,
    "TMP": 19
  },
  {
    "timestamp": "2026-01-20T08:26:26.000Z",
    "PM1": 4.7,
    "PM2.5": 4.9,
    "PM4": 4.9,
    "PM10": 4.9,
    "HUM1": 40.44,
    "TMP1": 19.26,
    "VOC": 162,
    "NOX": 1,
    "CO2": 474,
    "HUM2": 38.62,
    "TMP2": 19.18,
    "HUM": 40.65,
    "TMP": 18.99
  },
  {
    "timestamp": "2026-01-20T08:26:56.000Z",
    "PM1": 4.1,
    "PM2.5": 4.3,
    "PM4": 4.3,
    "PM10": 4.3,
    "HUM1": 40.43,
    "TMP1": 19.26,
    "VOC": 161,
    "NOX": 1,
    "CO2": 473,
    "HUM2": 38.62,
    "TMP2": 19.18,
    "HUM": 40.59,
    "TMP": 18.99
  },
  {
    "timestamp": "2026-01-20T08:27:26.000Z",
    "PM1": 5.2,
    "PM2.5": 5.4,
    "PM4": 5.4,
    "PM10": 5.4,
    "HUM1": 40.38,
    "TMP1": 19.26,
    "VOC": 161,
    "NOX": 1,
    "CO2": 473,
    "HUM2": 38.66,
    "TMP2": 19.18,
    "HUM": 40.62,
    "TMP": 18.98
  },
  {
    "timestamp": "2026-01-20T08:27:56.000Z",
    "PM1": 4.6,
    "PM2.5": 4.8,
    "PM4": 4.8,
    "PM10": 4.8,
    "HUM1": 40.39,
    "TMP1": 19.26,
    "VOC": 160,
    "NOX": 1,
    "CO2": 473,
    "HUM2": 38.64,
    "TMP2": 19.17,
    "HUM": 40.64,
    "TMP": 18.98
  },
  {
    "timestamp": "2026-01-20T08:28:26.000Z",
    "PM1": 4.3,
    "PM2.5": 4.5,
    "PM4": 4.5,
    "PM10": 4.5,
    "HUM1": 40.42,
    "TMP1": 19.26,
    "VOC": 159,
    "NOX": 1,
    "CO2": 472,
    "HUM2": 38.55,
    "TMP2": 19.15,
    "HUM": 40.55,
    "TMP": 18.98
  },
  {
    "timestamp": "2026-01-20T08:28:56.000Z",
    "PM1": 4.9,
    "PM2.5": 5.2,
    "PM4": 5.2,
    "PM10": 5.2,
    "HUM1": 40.36,
    "TMP1": 19.26,
    "VOC": 159,
    "NOX": 1,
    "CO2": 472,
    "HUM2": 38.63,
    "TMP2": 19.17,
    "HUM": 40.56,
    "TMP": 18.97
  },
  {
    "timestamp": "2026-01-20T08:29:26.000Z",
    "PM1": 5,
    "PM2.5": 5.3,
    "PM4": 5.3,
    "PM10": 5.3,
    "HUM1": 40.33,
    "TMP1": 19.25,
    "VOC": 159,
    "NOX": 1,
    "CO2": 473,
    "HUM2": 38.63,
    "TMP2": 19.18,
    "HUM": 40.64,
    "TMP": 18.99
  },
  {
    "timestamp": "2026-01-20T08:29:56.000Z",
    "PM1": 5,
    "PM2.5": 5.3,
    "PM4": 5.3,
    "PM10": 5.3,
    "HUM1": 40.31,
    "TMP1": 19.25,
    "VOC": 158,
    "NOX": 1,
    "CO2": 474,
    "HUM2": 38.65,
    "TMP2": 19.17,
    "HUM": 40.55,
    "TMP": 18.99
  },
  {
    "timestamp": "2026-01-20T08:30:26.000Z",
    "PM1": 4.6,
    "PM2.5": 4.8,
    "PM4": 4.8,
    "PM10": 4.8,
    "HUM1": 40.36,
    "TMP1": 19.25,
    "VOC": 157,
    "NOX": 1,
    "CO2": 474,
    "HUM2": 38.6,
    "TMP2": 19.16,
    "HUM": 40.48,
    "TMP": 18.95
  },
  {
    "timestamp": "2026-01-20T08:30:56.000Z",
    "PM1": 4.6,
    "PM2.5": 4.8,
    "PM4": 4.8,
    "PM10": 4.8,
    "HUM1": 40.41,
    "TMP1": 19.25,
    "VOC": 156,
    "NOX": 1,
    "CO2": 473,
    "HUM2": 38.52,
    "TMP2": 19.15,
    "HUM": 40.42,
    "TMP": 18.96
  },
  {
    "timestamp": "2026-01-20T08:31:27.000Z",
    "PM1": 4.7,
    "PM2.5": 4.9,
    "PM4": 4.9,
    "PM10": 4.9,
    "HUM1": 40.26,
    "TMP1": 19.25,
    "VOC": 155,
    "NOX": 1,
    "CO2": 472,
    "HUM2": 38.58,
    "TMP2": 19.16,
    "HUM": 40.54,
    "TMP": 18.98
  },
  {
    "timestamp": "2026-01-20T08:31:56.000Z",
    "PM1": 4.4,
    "PM2.5": 4.6,
    "PM4": 4.6,
    "PM10": 4.6,
    "HUM1": 40.28,
    "TMP1": 19.25,
    "VOC": 153,
    "NOX": 1,
    "CO2": 472,
    "HUM2": 38.56,
    "TMP2": 19.16,
    "HUM": 40.64,
    "TMP": 18.98
  },
  {
    "timestamp": "2026-01-20T08:32:26.000Z",
    "PM1": 4.8,
    "PM2.5": 5,
    "PM4": 5,
    "PM10": 5,
    "HUM1": 40.32,
    "TMP1": 19.25,
    "VOC": 152,
    "NOX": 1,
    "CO2": 472,
    "HUM2": 38.57,
    "TMP2": 19.16,
    "HUM": 40.46,
    "TMP": 18.98
  },
  {
    "timestamp": "2026-01-20T08:32:56.000Z",
    "PM1": 5.3,
    "PM2.5": 5.5,
    "PM4": 5.5,
    "PM10": 5.5,
    "HUM1": 40.33,
    "TMP1": 19.25,
    "VOC": 152,
    "NOX": 1,
    "CO2": 472,
    "HUM2": 38.53,
    "TMP2": 19.13,
    "HUM": 40.51,
    "TMP": 18.97
  },
  {
    "timestamp": "2026-01-20T08:33:26.000Z",
    "PM1": 4.2,
    "PM2.5": 4.4,
    "PM4": 4.4,
    "PM10": 4.4,
    "HUM1": 40.22,
    "TMP1": 19.25,
    "VOC": 150,
    "NOX": 1,
    "CO2": 474,
    "HUM2": 38.56,
    "TMP2": 19.14,
    "HUM": 40.55,
    "TMP": 18.96
  },
  {
    "timestamp": "2026-01-20T08:33:56.000Z",
    "PM1": 4.5,
    "PM2.5": 4.7,
    "PM4": 4.7,
    "PM10": 4.7,
    "HUM1": 40.27,
    "TMP1": 19.25,
    "VOC": 147,
    "NOX": 1,
    "CO2": 474,
    "HUM2": 38.53,
    "TMP2": 19.15,
    "HUM": 40.48,
    "TMP": 18.97
  },
  {
    "timestamp": "2026-01-20T08:34:26.000Z",
    "PM1": 4.8,
    "PM2.5": 5,
    "PM4": 5,
    "PM10": 5,
    "HUM1": 40.23,
    "TMP1": 19.25,
    "VOC": 146,
    "NOX": 1,
    "CO2": 471,
    "HUM2": 38.55,
    "TMP2": 19.15,
    "HUM": 40.55,
    "TMP": 18.95
  },
  {
    "timestamp": "2026-01-20T08:34:56.000Z",
    "PM1": 4.8,
    "PM2.5": 5.1,
    "PM4": 5.1,
    "PM10": 5.1,
    "HUM1": 40.26,
    "TMP1": 19.24,
    "VOC": 145,
    "NOX": 1,
    "CO2": 470,
    "HUM2": 38.54,
    "TMP2": 19.16,
    "HUM": 40.52,
    "TMP": 18.95
  },
  {
    "timestamp": "2026-01-20T08:35:26.000Z",
    "PM1": 4.5,
    "PM2.5": 4.7,
    "PM4": 4.7,
    "PM10": 4.7,
    "HUM1": 40.3,
    "TMP1": 19.24,
    "VOC": 144,
    "NOX": 1,
    "CO2": 470,
    "HUM2": 38.55,
    "TMP2": 19.18,
    "HUM": 40.47,
    "TMP": 18.97
  },
  {
    "timestamp": "2026-01-20T08:35:56.000Z",
    "PM1": 4.3,
    "PM2.5": 4.5,
    "PM4": 4.5,
    "PM10": 4.5,
    "HUM1": 40.25,
    "TMP1": 19.24,
    "VOC": 143,
    "NOX": 1,
    "CO2": 468,
    "HUM2": 38.56,
    "TMP2": 19.14,
    "HUM": 40.43,
    "TMP": 18.95
  },
  {
    "timestamp": "2026-01-20T08:36:26.000Z",
    "PM1": 4.5,
    "PM2.5": 4.8,
    "PM4": 4.8,
    "PM10": 4.8,
    "HUM1": 40.24,
    "TMP1": 19.24,
    "VOC": 143,
    "NOX": 1,
    "CO2": 467,
    "HUM2": 38.5,
    "TMP2": 19.15,
    "HUM": 40.48,
    "TMP": 18.95
  },
  {
    "timestamp": "2026-01-20T08:36:56.000Z",
    "PM1": 4.4,
    "PM2.5": 4.6,
    "PM4": 4.6,
    "PM10": 4.6,
    "HUM1": 40.2,
    "TMP1": 19.24,
    "VOC": 142,
    "NOX": 1,
    "CO2": 466,
    "HUM2": 38.53,
    "TMP2": 19.12,
    "HUM": 40.49,
    "TMP": 18.95
  },
  {
    "timestamp": "2026-01-20T08:37:26.000Z",
    "PM1": 4.4,
    "PM2.5": 4.7,
    "PM4": 4.7,
    "PM10": 4.7,
    "HUM1": 40.18,
    "TMP1": 19.24,
    "VOC": 140,
    "NOX": 1,
    "CO2": 467,
    "HUM2": 38.5,
    "TMP2": 19.15,
    "HUM": 40.54,
    "TMP": 18.96
  },
  {
    "timestamp": "2026-01-20T08:37:56.000Z",
    "PM1": 4.5,
    "PM2.5": 4.7,
    "PM4": 4.7,
    "PM10": 4.7,
    "HUM1": 40.17,
    "TMP1": 19.23,
    "VOC": 140,
    "NOX": 1,
    "CO2": 467,
    "HUM2": 38.53,
    "TMP2": 19.15,
    "HUM": 40.43,
    "TMP": 18.96
  },
  {
    "timestamp": "2026-01-20T08:38:26.000Z",
    "PM1": 4,
    "PM2.5": 4.1,
    "PM4": 4.1,
    "PM10": 4.1,
    "HUM1": 40.27,
    "TMP1": 19.23,
    "VOC": 140,
    "NOX": 1,
    "CO2": 467,
    "HUM2": 38.51,
    "TMP2": 19.14,
    "HUM": 40.4,
    "TMP": 18.95
  },
  {
    "timestamp": "2026-01-20T08:38:56.000Z",
    "PM1": 4.6,
    "PM2.5": 4.8,
    "PM4": 4.8,
    "PM10": 4.8,
    "HUM1": 40.24,
    "TMP1": 19.23,
    "VOC": 141,
    "NOX": 1,
    "CO2": 467,
    "HUM2": 38.46,
    "TMP2": 19.13,
    "HUM": 40.41,
    "TMP": 18.96
  },
  {
    "timestamp": "2026-01-20T08:39:26.000Z",
    "PM1": 4.3,
    "PM2.5": 4.5,
    "PM4": 4.5,
    "PM10": 4.5,
    "HUM1": 40.26,
    "TMP1": 19.22,
    "VOC": 141,
    "NOX": 1,
    "CO2": 467,
    "HUM2": 38.45,
    "TMP2": 19.13,
    "HUM": 40.44,
    "TMP": 18.96
  },
  {
    "timestamp": "2026-01-20T08:39:56.000Z",
    "PM1": 3.9,
    "PM2.5": 4.1,
    "PM4": 4.1,
    "PM10": 4.1,
    "HUM1": 40.34,
    "TMP1": 19.22,
    "VOC": 141,
    "NOX": 1,
    "CO2": 465,
    "HUM2": 38.47,
    "TMP2": 19.13,
    "HUM": 40.47,
    "TMP": 18.93
  },
  {
    "timestamp": "2026-01-20T08:40:26.000Z",
    "PM1": 4.2,
    "PM2.5": 4.4,
    "PM4": 4.4,
    "PM10": 4.4,
    "HUM1": 40.39,
    "TMP1": 19.22,
    "VOC": 142,
    "NOX": 1,
    "CO2": 465,
    "HUM2": 38.5,
    "TMP2": 19.12,
    "HUM": 40.47,
    "TMP": 18.95
  },
  {
    "timestamp": "2026-01-20T08:40:56.000Z",
    "PM1": 4.5,
    "PM2.5": 4.7,
    "PM4": 4.7,
    "PM10": 4.7,
    "HUM1": 40.4,
    "TMP1": 19.21,
    "VOC": 142,
    "NOX": 1,
    "CO2": 465,
    "HUM2": 38.5,
    "TMP2": 19.14,
    "HUM": 40.46,
    "TMP": 18.95
  },
  {
    "timestamp": "2026-01-20T08:41:26.000Z",
    "PM1": 4.3,
    "PM2.5": 4.5,
    "PM4": 4.5,
    "PM10": 4.5,
    "HUM1": 40.33,
    "TMP1": 19.21,
    "VOC": 142,
    "NOX": 1,
    "CO2": 465,
    "HUM2": 38.49,
    "TMP2": 19.16,
    "HUM": 40.51,
    "TMP": 18.95
  },
  {
    "timestamp": "2026-01-20T08:41:56.000Z",
    "PM1": 4.8,
    "PM2.5": 5.1,
    "PM4": 5.1,
    "PM10": 5.1,
    "HUM1": 40.38,
    "TMP1": 19.21,
    "VOC": 143,
    "NOX": 1,
    "CO2": 467,
    "HUM2": 38.53,
    "TMP2": 19.14,
    "HUM": 40.49,
    "TMP": 18.95
  },
  {
    "timestamp": "2026-01-20T08:42:26.000Z",
    "PM1": 4.1,
    "PM2.5": 4.3,
    "PM4": 4.3,
    "PM10": 4.3,
    "HUM1": 40.37,
    "TMP1": 19.2,
    "VOC": 143,
    "NOX": 1,
    "CO2": 467,
    "HUM2": 38.49,
    "TMP2": 19.13,
    "HUM": 40.51,
    "TMP": 18.93
  },
  {
    "timestamp": "2026-01-20T08:42:56.000Z",
    "PM1": 4.2,
    "PM2.5": 4.4,
    "PM4": 4.4,
    "PM10": 4.4,
    "HUM1": 40.34,
    "TMP1": 19.2,
    "VOC": 143,
    "NOX": 1,
    "CO2": 465,
    "HUM2": 38.58,
    "TMP2": 19.11,
    "HUM": 40.51,
    "TMP": 18.95
  },
  {
    "timestamp": "2026-01-20T08:43:26.000Z",
    "PM1": 4.1,
    "PM2.5": 4.3,
    "PM4": 4.3,
    "PM10": 4.3,
    "HUM1": 40.39,
    "TMP1": 19.2,
    "VOC": 144,
    "NOX": 1,
    "CO2": 463,
    "HUM2": 38.53,
    "TMP2": 19.12,
    "HUM": 40.51,
    "TMP": 18.94
  },
  {
    "timestamp": "2026-01-20T08:43:56.000Z",
    "PM1": 4.5,
    "PM2.5": 4.7,
    "PM4": 4.7,
    "PM10": 4.7,
    "HUM1": 40.44,
    "TMP1": 19.2,
    "VOC": 144,
    "NOX": 1,
    "CO2": 464,
    "HUM2": 38.58,
    "TMP2": 19.12,
    "HUM": 40.54,
    "TMP": 18.93
  },
  {
    "timestamp": "2026-01-20T08:44:26.000Z",
    "PM1": 5,
    "PM2.5": 5.2,
    "PM4": 5.2,
    "PM10": 5.2,
    "HUM1": 40.45,
    "TMP1": 19.2,
    "VOC": 145,
    "NOX": 1,
    "CO2": 465,
    "HUM2": 38.56,
    "TMP2": 19.13,
    "HUM": 40.6,
    "TMP": 18.96
  },
  {
    "timestamp": "2026-01-20T08:44:56.000Z",
    "PM1": 5,
    "PM2.5": 5.3,
    "PM4": 5.3,
    "PM10": 5.3,
    "HUM1": 40.45,
    "TMP1": 19.2,
    "VOC": 146,
    "NOX": 1,
    "CO2": 465,
    "HUM2": 38.61,
    "TMP2": 19.14,
    "HUM": 40.56,
    "TMP": 18.93
  },
  {
    "timestamp": "2026-01-20T08:45:26.000Z",
    "PM1": 4.2,
    "PM2.5": 4.5,
    "PM4": 4.5,
    "PM10": 4.5,
    "HUM1": 40.47,
    "TMP1": 19.19,
    "VOC": 148,
    "NOX": 1,
    "CO2": 465,
    "HUM2": 38.59,
    "TMP2": 19.13,
    "HUM": 40.6,
    "TMP": 18.95
  },
  {
    "timestamp": "2026-01-20T08:45:56.000Z",
    "PM1": 4.4,
    "PM2.5": 4.6,
    "PM4": 4.6,
    "PM10": 4.6,
    "HUM1": 40.51,
    "TMP1": 19.19,
    "VOC": 149,
    "NOX": 1,
    "CO2": 465,
    "HUM2": 38.58,
    "TMP2": 19.13,
    "HUM": 40.65,
    "TMP": 18.92
  },
  {
    "timestamp": "2026-01-20T08:46:26.000Z",
    "PM1": 4.3,
    "PM2.5": 4.5,
    "PM4": 4.5,
    "PM10": 4.5,
    "HUM1": 40.54,
    "TMP1": 19.19,
    "VOC": 151,
    "NOX": 1,
    "CO2": 465,
    "HUM2": 38.66,
    "TMP2": 19.13,
    "HUM": 40.72,
    "TMP": 18.93
  },
  {
    "timestamp": "2026-01-20T08:46:55.000Z",
    "PM1": 4,
    "PM2.5": 4.2,
    "PM4": 4.2,
    "PM10": 4.2,
    "HUM1": 40.55,
    "TMP1": 19.19,
    "VOC": 154,
    "NOX": 1,
    "CO2": 466,
    "HUM2": 38.68,
    "TMP2": 19.1,
    "HUM": 40.68,
    "TMP": 18.94
  },
  {
    "timestamp": "2026-01-20T08:47:25.000Z",
    "PM1": 4.4,
    "PM2.5": 4.6,
    "PM4": 4.6,
    "PM10": 4.6,
    "HUM1": 40.58,
    "TMP1": 19.19,
    "VOC": 157,
    "NOX": 1,
    "CO2": 467,
    "HUM2": 38.69,
    "TMP2": 19.13,
    "HUM": 40.65,
    "TMP": 18.94
  },
  {
    "timestamp": "2026-01-20T08:47:55.000Z",
    "PM1": 4.5,
    "PM2.5": 4.7,
    "PM4": 4.7,
    "PM10": 4.7,
    "HUM1": 40.56,
    "TMP1": 19.18,
    "VOC": 157,
    "NOX": 1,
    "CO2": 467,
    "HUM2": 38.68,
    "TMP2": 19.12,
    "HUM": 40.73,
    "TMP": 18.94
  },
  {
    "timestamp": "2026-01-20T08:48:25.000Z",
    "PM1": 4.7,
    "PM2.5": 4.9,
    "PM4": 4.9,
    "PM10": 4.9,
    "HUM1": 40.64,
    "TMP1": 19.18,
    "VOC": 157,
    "NOX": 1,
    "CO2": 468,
    "HUM2": 38.69,
    "TMP2": 19.11,
    "HUM": 40.74,
    "TMP": 18.94
  },
  {
    "timestamp": "2026-01-20T08:48:55.000Z",
    "PM1": 4.2,
    "PM2.5": 4.4,
    "PM4": 4.4,
    "PM10": 4.4,
    "HUM1": 40.65,
    "TMP1": 19.18,
    "VOC": 159,
    "NOX": 1,
    "CO2": 470,
    "HUM2": 38.7,
    "TMP2": 19.12,
    "HUM": 40.76,
    "TMP": 18.93
  },
  {
    "timestamp": "2026-01-20T08:49:25.000Z",
    "PM1": 3.9,
    "PM2.5": 4.1,
    "PM4": 4.1,
    "PM10": 4.1,
    "HUM1": 40.63,
    "TMP1": 19.18,
    "VOC": 160,
    "NOX": 1,
    "CO2": 470,
    "HUM2": 38.68,
    "TMP2": 19.12,
    "HUM": 40.67,
    "TMP": 18.93
  },
  {
    "timestamp": "2026-01-20T08:49:55.000Z",
    "PM1": 4.5,
    "PM2.5": 4.7,
    "PM4": 4.7,
    "PM10": 4.7,
    "HUM1": 40.66,
    "TMP1": 19.18,
    "VOC": 161,
    "NOX": 1,
    "CO2": 471,
    "HUM2": 38.72,
    "TMP2": 19.14,
    "HUM": 40.77,
    "TMP": 18.95
  },
  {
    "timestamp": "2026-01-20T08:50:25.000Z",
    "PM1": 4.2,
    "PM2.5": 4.4,
    "PM4": 4.4,
    "PM10": 4.4,
    "HUM1": 40.69,
    "TMP1": 19.18,
    "VOC": 163,
    "NOX": 1,
    "CO2": 470,
    "HUM2": 38.77,
    "TMP2": 19.12,
    "HUM": 40.74,
    "TMP": 18.92
  },
  {
    "timestamp": "2026-01-20T08:50:55.000Z",
    "PM1": 4.3,
    "PM2.5": 4.5,
    "PM4": 4.5,
    "PM10": 4.5,
    "HUM1": 40.72,
    "TMP1": 19.17,
    "VOC": 166,
    "NOX": 1,
    "CO2": 469,
    "HUM2": 38.71,
    "TMP2": 19.11,
    "HUM": 40.76,
    "TMP": 18.91
  },
  {
    "timestamp": "2026-01-20T08:51:25.000Z",
    "PM1": 4.2,
    "PM2.5": 4.4,
    "PM4": 4.4,
    "PM10": 4.4,
    "HUM1": 40.69,
    "TMP1": 19.17,
    "VOC": 166,
    "NOX": 1,
    "CO2": 470,
    "HUM2": 38.76,
    "TMP2": 19.13,
    "HUM": 40.71,
    "TMP": 18.92
  },
  {
    "timestamp": "2026-01-20T08:51:55.000Z",
    "PM1": 4.6,
    "PM2.5": 4.9,
    "PM4": 4.9,
    "PM10": 4.9,
    "HUM1": 40.7,
    "TMP1": 19.17,
    "VOC": 166,
    "NOX": 1,
    "CO2": 470,
    "HUM2": 38.71,
    "TMP2": 19.11,
    "HUM": 40.8,
    "TMP": 18.93
  },
  {
    "timestamp": "2026-01-20T08:52:25.000Z",
    "PM1": 4.4,
    "PM2.5": 4.6,
    "PM4": 4.6,
    "PM10": 4.6,
    "HUM1": 40.7,
    "TMP1": 19.17,
    "VOC": 167,
    "NOX": 1,
    "CO2": 470,
    "HUM2": 38.74,
    "TMP2": 19.13,
    "HUM": 40.78,
    "TMP": 18.92
  },
  {
    "timestamp": "2026-01-20T08:52:55.000Z",
    "PM1": 5,
    "PM2.5": 5.3,
    "PM4": 5.3,
    "PM10": 5.3,
    "HUM1": 40.73,
    "TMP1": 19.17,
    "VOC": 168,
    "NOX": 1,
    "CO2": 470,
    "HUM2": 38.8,
    "TMP2": 19.12,
    "HUM": 40.78,
    "TMP": 18.92
  },
  {
    "timestamp": "2026-01-20T08:53:25.000Z",
    "PM1": 4.3,
    "PM2.5": 4.5,
    "PM4": 4.5,
    "PM10": 4.5,
    "HUM1": 40.72,
    "TMP1": 19.17,
    "VOC": 167,
    "NOX": 1,
    "CO2": 471,
    "HUM2": 38.8,
    "TMP2": 19.1,
    "HUM": 40.81,
    "TMP": 18.92
  },
  {
    "timestamp": "2026-01-20T08:53:55.000Z",
    "PM1": 4.5,
    "PM2.5": 4.7,
    "PM4": 4.7,
    "PM10": 4.7,
    "HUM1": 40.72,
    "TMP1": 19.17,
    "VOC": 167,
    "NOX": 1,
    "CO2": 470,
    "HUM2": 38.8,
    "TMP2": 19.11,
    "HUM": 40.77,
    "TMP": 18.93
  },
  {
    "timestamp": "2026-01-20T08:54:25.000Z",
    "PM1": 4.8,
    "PM2.5": 5.1,
    "PM4": 5.1,
    "PM10": 5.1,
    "HUM1": 40.72,
    "TMP1": 19.16,
    "VOC": 167,
    "NOX": 1,
    "CO2": 471,
    "HUM2": 38.79,
    "TMP2": 19.09,
    "HUM": 40.82,
    "TMP": 18.9
  },
  {
    "timestamp": "2026-01-20T08:54:55.000Z",
    "PM1": 4.7,
    "PM2.5": 4.9,
    "PM4": 4.9,
    "PM10": 4.9,
    "HUM1": 40.73,
    "TMP1": 19.16,
    "VOC": 167,
    "NOX": 1,
    "CO2": 471,
    "HUM2": 38.81,
    "TMP2": 19.12,
    "HUM": 40.8,
    "TMP": 18.91
  },
  {
    "timestamp": "2026-01-20T08:55:25.000Z",
    "PM1": 4.8,
    "PM2.5": 5,
    "PM4": 5,
    "PM10": 5,
    "HUM1": 40.73,
    "TMP1": 19.16,
    "VOC": 169,
    "NOX": 1,
    "CO2": 472,
    "HUM2": 38.84,
    "TMP2": 19.1,
    "HUM": 40.81,
    "TMP": 18.91
  },
  {
    "timestamp": "2026-01-20T08:55:55.000Z",
    "PM1": 4.2,
    "PM2.5": 4.4,
    "PM4": 4.4,
    "PM10": 4.4,
    "HUM1": 40.75,
    "TMP1": 19.16,
    "VOC": 170,
    "NOX": 1,
    "CO2": 473,
    "HUM2": 38.78,
    "TMP2": 19.11,
    "HUM": 40.83,
    "TMP": 18.9
  },
  {
    "timestamp": "2026-01-20T08:56:25.000Z",
    "PM1": 4.3,
    "PM2.5": 4.5,
    "PM4": 4.5,
    "PM10": 4.5,
    "HUM1": 40.77,
    "TMP1": 19.16,
    "VOC": 170,
    "NOX": 1,
    "CO2": 474,
    "HUM2": 38.81,
    "TMP2": 19.1,
    "HUM": 40.86,
    "TMP": 18.9
  },
  {
    "timestamp": "2026-01-20T08:56:55.000Z",
    "PM1": 4.4,
    "PM2.5": 4.6,
    "PM4": 4.6,
    "PM10": 4.6,
    "HUM1": 40.76,
    "TMP1": 19.16,
    "VOC": 170,
    "NOX": 1,
    "CO2": 474,
    "HUM2": 38.86,
    "TMP2": 19.1,
    "HUM": 40.92,
    "TMP": 18.9
  },
  {
    "timestamp": "2026-01-20T08:57:25.000Z",
    "PM1": 4.7,
    "PM2.5": 4.9,
    "PM4": 4.9,
    "PM10": 4.9,
    "HUM1": 40.68,
    "TMP1": 19.16,
    "VOC": 169,
    "NOX": 1,
    "CO2": 474,
    "HUM2": 38.89,
    "TMP2": 19.11,
    "HUM": 40.83,
    "TMP": 18.91
  },
  {
    "timestamp": "2026-01-20T08:57:55.000Z",
    "PM1": 4.3,
    "PM2.5": 4.5,
    "PM4": 4.5,
    "PM10": 4.5,
    "HUM1": 40.67,
    "TMP1": 19.16,
    "VOC": 169,
    "NOX": 1,
    "CO2": 474,
    "HUM2": 38.81,
    "TMP2": 19.08,
    "HUM": 40.8,
    "TMP": 18.91
  },
  {
    "timestamp": "2026-01-20T08:58:25.000Z",
    "PM1": 4.7,
    "PM2.5": 4.9,
    "PM4": 4.9,
    "PM10": 4.9,
    "HUM1": 40.63,
    "TMP1": 19.16,
    "VOC": 168,
    "NOX": 1,
    "CO2": 474,
    "HUM2": 38.81,
    "TMP2": 19.09,
    "HUM": 40.77,
    "TMP": 18.91
  },
  {
    "timestamp": "2026-01-20T08:58:55.000Z",
    "PM1": 4.5,
    "PM2.5": 4.7,
    "PM4": 4.7,
    "PM10": 4.7,
    "HUM1": 40.59,
    "TMP1": 19.16,
    "VOC": 168,
    "NOX": 1,
    "CO2": 473,
    "HUM2": 38.8,
    "TMP2": 19.08,
    "HUM": 40.81,
    "TMP": 18.9
  },
  {
    "timestamp": "2026-01-20T08:59:25.000Z",
    "PM1": 4.4,
    "PM2.5": 4.6,
    "PM4": 4.6,
    "PM10": 4.6,
    "HUM1": 40.55,
    "TMP1": 19.16,
    "VOC": 167,
    "NOX": 1,
    "CO2": 473,
    "HUM2": 38.83,
    "TMP2": 19.08,
    "HUM": 40.77,
    "TMP": 18.9
  },
  {
    "timestamp": "2026-01-20T08:59:55.000Z",
    "PM1": 3.7,
    "PM2.5": 3.9,
    "PM4": 3.9,
    "PM10": 3.9,
    "HUM1": 40.57,
    "TMP1": 19.16,
    "VOC": 164,
    "NOX": 1,
    "CO2": 472,
    "HUM2": 38.87,
    "TMP2": 19.06,
    "HUM": 40.8,
    "TMP": 18.89
  },
  {
    "timestamp": "2026-01-20T09:00:25.000Z",
    "PM1": 4,
    "PM2.5": 4.2,
    "PM4": 4.2,
    "PM10": 4.2,
    "HUM1": 40.58,
    "TMP1": 19.16,
    "VOC": 162,
    "NOX": 1,
    "CO2": 471,
    "HUM2": 38.81,
    "TMP2": 19.05,
    "HUM": 40.79,
    "TMP": 18.88
  },
  {
    "timestamp": "2026-01-20T09:00:55.000Z",
    "PM1": 4.3,
    "PM2.5": 4.5,
    "PM4": 4.5,
    "PM10": 4.5,
    "HUM1": 40.54,
    "TMP1": 19.16,
    "VOC": 160,
    "NOX": 1,
    "CO2": 472,
    "HUM2": 38.81,
    "TMP2": 19.05,
    "HUM": 40.76,
    "TMP": 18.88
  },
  {
    "timestamp": "2026-01-20T09:01:25.000Z",
    "PM1": 4,
    "PM2.5": 4.2,
    "PM4": 4.2,
    "PM10": 4.2,
    "HUM1": 40.54,
    "TMP1": 19.16,
    "VOC": 159,
    "NOX": 1,
    "CO2": 471,
    "HUM2": 38.8,
    "TMP2": 19.07,
    "HUM": 40.73,
    "TMP": 18.86
  },
  {
    "timestamp": "2026-01-20T09:01:55.000Z",
    "PM1": 4.4,
    "PM2.5": 4.6,
    "PM4": 4.6,
    "PM10": 4.6,
    "HUM1": 40.49,
    "TMP1": 19.16,
    "VOC": 155,
    "NOX": 1,
    "CO2": 471,
    "HUM2": 38.75,
    "TMP2": 19.06,
    "HUM": 40.71,
    "TMP": 18.88
  },
  {
    "timestamp": "2026-01-20T09:02:25.000Z",
    "PM1": 3.9,
    "PM2.5": 4.1,
    "PM4": 4.1,
    "PM10": 4.1,
    "HUM1": 40.51,
    "TMP1": 19.16,
    "VOC": 154,
    "NOX": 1,
    "CO2": 470,
    "HUM2": 38.78,
    "TMP2": 19.06,
    "HUM": 40.7,
    "TMP": 18.87
  },
  {
    "timestamp": "2026-01-20T09:02:55.000Z",
    "PM1": 3.5,
    "PM2.5": 3.7,
    "PM4": 3.7,
    "PM10": 3.7,
    "HUM1": 40.54,
    "TMP1": 19.16,
    "VOC": 153,
    "NOX": 1,
    "CO2": 466,
    "HUM2": 38.73,
    "TMP2": 19.06,
    "HUM": 40.7,
    "TMP": 18.87
  },
  {
    "timestamp": "2026-01-20T09:03:25.000Z",
    "PM1": 3.7,
    "PM2.5": 3.9,
    "PM4": 3.9,
    "PM10": 3.9,
    "HUM1": 40.5,
    "TMP1": 19.15,
    "VOC": 151,
    "NOX": 1,
    "CO2": 465,
    "HUM2": 38.78,
    "TMP2": 19.08,
    "HUM": 40.72,
    "TMP": 18.9
  },
  {
    "timestamp": "2026-01-20T09:03:55.000Z",
    "PM1": 4.1,
    "PM2.5": 4.3,
    "PM4": 4.3,
    "PM10": 4.3,
    "HUM1": 40.57,
    "TMP1": 19.15,
    "VOC": 151,
    "NOX": 1,
    "CO2": 465,
    "HUM2": 38.75,
    "TMP2": 19.06,
    "HUM": 40.76,
    "TMP": 18.88
  },
  {
    "timestamp": "2026-01-20T09:04:25.000Z",
    "PM1": 4.1,
    "PM2.5": 4.3,
    "PM4": 4.3,
    "PM10": 4.3,
    "HUM1": 40.61,
    "TMP1": 19.15,
    "VOC": 150,
    "NOX": 1,
    "CO2": 464,
    "HUM2": 38.77,
    "TMP2": 19.05,
    "HUM": 40.82,
    "TMP": 18.89
  },
  {
    "timestamp": "2026-01-20T09:04:55.000Z",
    "PM1": 4,
    "PM2.5": 4.2,
    "PM4": 4.2,
    "PM10": 4.2,
    "HUM1": 40.59,
    "TMP1": 19.15,
    "VOC": 150,
    "NOX": 1,
    "CO2": 463,
    "HUM2": 38.84,
    "TMP2": 19.05,
    "HUM": 40.75,
    "TMP": 18.88
  },
  {
    "timestamp": "2026-01-20T09:05:25.000Z",
    "PM1": 4,
    "PM2.5": 4.2,
    "PM4": 4.2,
    "PM10": 4.2,
    "HUM1": 40.6,
    "TMP1": 19.15,
    "VOC": 150,
    "NOX": 1,
    "CO2": 464,
    "HUM2": 38.83,
    "TMP2": 19.07,
    "HUM": 40.79,
    "TMP": 18.86
  },
  {
    "timestamp": "2026-01-20T09:05:55.000Z",
    "PM1": 4.1,
    "PM2.5": 4.3,
    "PM4": 4.3,
    "PM10": 4.3,
    "HUM1": 40.66,
    "TMP1": 19.14,
    "VOC": 150,
    "NOX": 1,
    "CO2": 464,
    "HUM2": 38.84,
    "TMP2": 19.09,
    "HUM": 40.81,
    "TMP": 18.87
  },
  {
    "timestamp": "2026-01-20T09:06:25.000Z",
    "PM1": 3.7,
    "PM2.5": 3.8,
    "PM4": 3.8,
    "PM10": 3.8,
    "HUM1": 40.64,
    "TMP1": 19.14,
    "VOC": 150,
    "NOX": 1,
    "CO2": 465,
    "HUM2": 38.81,
    "TMP2": 19.07,
    "HUM": 40.85,
    "TMP": 18.86
  },
  {
    "timestamp": "2026-01-20T09:06:55.000Z",
    "PM1": 3.8,
    "PM2.5": 3.9,
    "PM4": 3.9,
    "PM10": 3.9,
    "HUM1": 40.63,
    "TMP1": 19.14,
    "VOC": 150,
    "NOX": 1,
    "CO2": 465,
    "HUM2": 38.84,
    "TMP2": 19.06,
    "HUM": 40.82,
    "TMP": 18.88
  },
  {
    "timestamp": "2026-01-20T09:07:25.000Z",
    "PM1": 3.7,
    "PM2.5": 3.9,
    "PM4": 3.9,
    "PM10": 3.9,
    "HUM1": 40.62,
    "TMP1": 19.14,
    "VOC": 151,
    "NOX": 1,
    "CO2": 464,
    "HUM2": 38.82,
    "TMP2": 19.04,
    "HUM": 40.76,
    "TMP": 18.86
  },
  {
    "timestamp": "2026-01-20T09:07:55.000Z",
    "PM1": 4.3,
    "PM2.5": 4.5,
    "PM4": 4.5,
    "PM10": 4.5,
    "HUM1": 40.61,
    "TMP1": 19.14,
    "VOC": 150,
    "NOX": 1,
    "CO2": 465,
    "HUM2": 38.82,
    "TMP2": 19.05,
    "HUM": 40.81,
    "TMP": 18.86
  },
  {
    "timestamp": "2026-01-20T09:08:25.000Z",
    "PM1": 4.9,
    "PM2.5": 5.1,
    "PM4": 5.1,
    "PM10": 5.1,
    "HUM1": 40.65,
    "TMP1": 19.14,
    "VOC": 150,
    "NOX": 1,
    "CO2": 467,
    "HUM2": 38.87,
    "TMP2": 19.05,
    "HUM": 40.81,
    "TMP": 18.85
  },
  {
    "timestamp": "2026-01-20T09:08:55.000Z",
    "PM1": 3.9,
    "PM2.5": 4.1,
    "PM4": 4.1,
    "PM10": 4.1,
    "HUM1": 40.64,
    "TMP1": 19.14,
    "VOC": 150,
    "NOX": 1,
    "CO2": 467,
    "HUM2": 38.89,
    "TMP2": 19.03,
    "HUM": 40.84,
    "TMP": 18.88
  },
  {
    "timestamp": "2026-01-20T09:09:25.000Z",
    "PM1": 4.2,
    "PM2.5": 4.4,
    "PM4": 4.4,
    "PM10": 4.4,
    "HUM1": 40.67,
    "TMP1": 19.13,
    "VOC": 150,
    "NOX": 1,
    "CO2": 466,
    "HUM2": 38.87,
    "TMP2": 19.05,
    "HUM": 40.79,
    "TMP": 18.87
  },
  {
    "timestamp": "2026-01-20T09:09:55.000Z",
    "PM1": 3.9,
    "PM2.5": 4.1,
    "PM4": 4.1,
    "PM10": 4.1,
    "HUM1": 40.58,
    "TMP1": 19.13,
    "VOC": 150,
    "NOX": 1,
    "CO2": 464,
    "HUM2": 38.86,
    "TMP2": 19.05,
    "HUM": 40.82,
    "TMP": 18.86
  },
  {
    "timestamp": "2026-01-20T09:10:25.000Z",
    "PM1": 4.1,
    "PM2.5": 4.3,
    "PM4": 4.3,
    "PM10": 4.3,
    "HUM1": 40.58,
    "TMP1": 19.13,
    "VOC": 149,
    "NOX": 1,
    "CO2": 463,
    "HUM2": 38.82,
    "TMP2": 19.04,
    "HUM": 40.83,
    "TMP": 18.86
  },
  {
    "timestamp": "2026-01-20T09:10:55.000Z",
    "PM1": 3.9,
    "PM2.5": 4.1,
    "PM4": 4.1,
    "PM10": 4.1,
    "HUM1": 40.62,
    "TMP1": 19.13,
    "VOC": 149,
    "NOX": 1,
    "CO2": 462,
    "HUM2": 38.89,
    "TMP2": 19.05,
    "HUM": 40.84,
    "TMP": 18.87
  },
  {
    "timestamp": "2026-01-20T09:11:25.000Z",
    "PM1": 3.8,
    "PM2.5": 3.9,
    "PM4": 3.9,
    "PM10": 3.9,
    "HUM1": 40.66,
    "TMP1": 19.13,
    "VOC": 150,
    "NOX": 1,
    "CO2": 462,
    "HUM2": 38.9,
    "TMP2": 19.03,
    "HUM": 40.86,
    "TMP": 18.85
  },
  {
    "timestamp": "2026-01-20T09:11:55.000Z",
    "PM1": 4.1,
    "PM2.5": 4.3,
    "PM4": 4.3,
    "PM10": 4.3,
    "HUM1": 40.7,
    "TMP1": 19.13,
    "VOC": 150,
    "NOX": 1,
    "CO2": 462,
    "HUM2": 38.92,
    "TMP2": 19.02,
    "HUM": 40.88,
    "TMP": 18.84
  },
  {
    "timestamp": "2026-01-20T09:12:25.000Z",
    "PM1": 4,
    "PM2.5": 4.2,
    "PM4": 4.2,
    "PM10": 4.2,
    "HUM1": 40.62,
    "TMP1": 19.13,
    "VOC": 150,
    "NOX": 1,
    "CO2": 463,
    "HUM2": 38.89,
    "TMP2": 19.02,
    "HUM": 40.82,
    "TMP": 18.85
  },
  {
    "timestamp": "2026-01-20T09:12:55.000Z",
    "PM1": 4.1,
    "PM2.5": 4.3,
    "PM4": 4.3,
    "PM10": 4.3,
    "HUM1": 40.41,
    "TMP1": 19.13,
    "VOC": 149,
    "NOX": 1,
    "CO2": 463,
    "HUM2": 38.85,
    "TMP2": 19.01,
    "HUM": 40.72,
    "TMP": 18.85
  },
  {
    "timestamp": "2026-01-20T09:13:25.000Z",
    "PM1": 4.2,
    "PM2.5": 4.4,
    "PM4": 4.4,
    "PM10": 4.4,
    "HUM1": 40.42,
    "TMP1": 19.13,
    "VOC": 147,
    "NOX": 1,
    "CO2": 462,
    "HUM2": 38.82,
    "TMP2": 19.03,
    "HUM": 40.75,
    "TMP": 18.85
  },
  {
    "timestamp": "2026-01-20T09:13:55.000Z",
    "PM1": 4.1,
    "PM2.5": 4.4,
    "PM4": 4.4,
    "PM10": 4.4,
    "HUM1": 40.34,
    "TMP1": 19.13,
    "VOC": 143,
    "NOX": 1,
    "CO2": 462,
    "HUM2": 38.82,
    "TMP2": 19.02,
    "HUM": 40.74,
    "TMP": 18.82
  },
  {
    "timestamp": "2026-01-20T09:14:25.000Z",
    "PM1": 3.7,
    "PM2.5": 3.9,
    "PM4": 3.9,
    "PM10": 3.9,
    "HUM1": 40.33,
    "TMP1": 19.13,
    "VOC": 140,
    "NOX": 1,
    "CO2": 460,
    "HUM2": 38.75,
    "TMP2": 19.01,
    "HUM": 40.64,
    "TMP": 18.84
  },
  {
    "timestamp": "2026-01-20T09:14:55.000Z",
    "PM1": 4,
    "PM2.5": 4.2,
    "PM4": 4.2,
    "PM10": 4.2,
    "HUM1": 40.23,
    "TMP1": 19.13,
    "VOC": 132,
    "NOX": 1,
    "CO2": 460,
    "HUM2": 38.8,
    "TMP2": 19.01,
    "HUM": 40.64,
    "TMP": 18.84
  },
  {
    "timestamp": "2026-01-20T09:15:25.000Z",
    "PM1": 4.5,
    "PM2.5": 4.8,
    "PM4": 4.8,
    "PM10": 4.8,
    "HUM1": 40.28,
    "TMP1": 19.13,
    "VOC": 132,
    "NOX": 1,
    "CO2": 460,
    "HUM2": 38.78,
    "TMP2": 19.01,
    "HUM": 40.66,
    "TMP": 18.83
  },
  {
    "timestamp": "2026-01-20T09:15:55.000Z",
    "PM1": 3.3,
    "PM2.5": 3.4,
    "PM4": 3.4,
    "PM10": 3.4,
    "HUM1": 40.15,
    "TMP1": 19.13,
    "VOC": 127,
    "NOX": 1,
    "CO2": 460,
    "HUM2": 38.75,
    "TMP2": 19,
    "HUM": 40.61,
    "TMP": 18.84
  },
  {
    "timestamp": "2026-01-20T09:16:25.000Z",
    "PM1": 3,
    "PM2.5": 3.1,
    "PM4": 3.1,
    "PM10": 3.1,
    "HUM1": 40.2,
    "TMP1": 19.12,
    "VOC": 121,
    "NOX": 1,
    "CO2": 459,
    "HUM2": 38.73,
    "TMP2": 19.02,
    "HUM": 40.53,
    "TMP": 18.82
  },
  {
    "timestamp": "2026-01-20T09:16:55.000Z",
    "PM1": 3.5,
    "PM2.5": 3.7,
    "PM4": 3.7,
    "PM10": 3.7,
    "HUM1": 40.19,
    "TMP1": 19.12,
    "VOC": 122,
    "NOX": 1,
    "CO2": 458,
    "HUM2": 38.68,
    "TMP2": 18.99,
    "HUM": 40.66,
    "TMP": 18.83
  },
  {
    "timestamp": "2026-01-20T09:17:25.000Z",
    "PM1": 3.5,
    "PM2.5": 3.6,
    "PM4": 3.6,
    "PM10": 3.6,
    "HUM1": 40.17,
    "TMP1": 19.11,
    "VOC": 122,
    "NOX": 1,
    "CO2": 457,
    "HUM2": 38.73,
    "TMP2": 19.01,
    "HUM": 40.6,
    "TMP": 18.85
  },
  {
    "timestamp": "2026-01-20T09:17:55.000Z",
    "PM1": 3.1,
    "PM2.5": 3.2,
    "PM4": 3.2,
    "PM10": 3.2,
    "HUM1": 40.31,
    "TMP1": 19.11,
    "VOC": 123,
    "NOX": 1,
    "CO2": 457,
    "HUM2": 38.69,
    "TMP2": 19,
    "HUM": 40.53,
    "TMP": 18.84
  },
  {
    "timestamp": "2026-01-20T09:18:25.000Z",
    "PM1": 3.1,
    "PM2.5": 3.3,
    "PM4": 3.3,
    "PM10": 3.3,
    "HUM1": 40.29,
    "TMP1": 19.11,
    "VOC": 126,
    "NOX": 1,
    "CO2": 458,
    "HUM2": 38.69,
    "TMP2": 19.03,
    "HUM": 40.57,
    "TMP": 18.8
  },
  {
    "timestamp": "2026-01-20T09:18:55.000Z",
    "PM1": 3.8,
    "PM2.5": 4,
    "PM4": 4,
    "PM10": 4,
    "HUM1": 40.24,
    "TMP1": 19.11,
    "VOC": 126,
    "NOX": 1,
    "CO2": 456,
    "HUM2": 38.65,
    "TMP2": 19.02,
    "HUM": 40.5,
    "TMP": 18.8
  },
  {
    "timestamp": "2026-01-20T09:19:25.000Z",
    "PM1": 3.8,
    "PM2.5": 4,
    "PM4": 4,
    "PM10": 4,
    "HUM1": 40.29,
    "TMP1": 19.11,
    "VOC": 126,
    "NOX": 1,
    "CO2": 456,
    "HUM2": 38.67,
    "TMP2": 19.01,
    "HUM": 40.58,
    "TMP": 18.83
  },
  {
    "timestamp": "2026-01-20T09:19:55.000Z",
    "PM1": 3,
    "PM2.5": 3.2,
    "PM4": 3.2,
    "PM10": 3.2,
    "HUM1": 40.41,
    "TMP1": 19.11,
    "VOC": 128,
    "NOX": 1,
    "CO2": 458,
    "HUM2": 38.69,
    "TMP2": 19,
    "HUM": 40.56,
    "TMP": 18.83
  },
  {
    "timestamp": "2026-01-20T09:20:25.000Z",
    "PM1": 3.7,
    "PM2.5": 3.9,
    "PM4": 3.9,
    "PM10": 3.9,
    "HUM1": 40.5,
    "TMP1": 19.1,
    "VOC": 129,
    "NOX": 1,
    "CO2": 458,
    "HUM2": 38.65,
    "TMP2": 19,
    "HUM": 40.59,
    "TMP": 18.81
  },
  {
    "timestamp": "2026-01-20T09:20:55.000Z",
    "PM1": 4,
    "PM2.5": 4.2,
    "PM4": 4.2,
    "PM10": 4.2,
    "HUM1": 40.45,
    "TMP1": 19.09,
    "VOC": 129,
    "NOX": 1,
    "CO2": 457,
    "HUM2": 38.7,
    "TMP2": 19.01,
    "HUM": 40.62,
    "TMP": 18.82
  },
  {
    "timestamp": "2026-01-20T09:21:25.000Z",
    "PM1": 3.7,
    "PM2.5": 3.8,
    "PM4": 3.8,
    "PM10": 3.8,
    "HUM1": 40.42,
    "TMP1": 19.09,
    "VOC": 130,
    "NOX": 1,
    "CO2": 456,
    "HUM2": 38.71,
    "TMP2": 19,
    "HUM": 40.65,
    "TMP": 18.82
  },
  {
    "timestamp": "2026-01-20T09:21:55.000Z",
    "PM1": 3.5,
    "PM2.5": 3.6,
    "PM4": 3.6,
    "PM10": 3.6,
    "HUM1": 40.49,
    "TMP1": 19.08,
    "VOC": 130,
    "NOX": 1,
    "CO2": 456,
    "HUM2": 38.75,
    "TMP2": 19.01,
    "HUM": 40.71,
    "TMP": 18.81
  },
  {
    "timestamp": "2026-01-20T09:22:25.000Z",
    "PM1": 3.3,
    "PM2.5": 3.5,
    "PM4": 3.5,
    "PM10": 3.5,
    "HUM1": 40.5,
    "TMP1": 19.08,
    "VOC": 131,
    "NOX": 1,
    "CO2": 456,
    "HUM2": 38.72,
    "TMP2": 19,
    "HUM": 40.66,
    "TMP": 18.8
  },
  {
    "timestamp": "2026-01-20T09:22:55.000Z",
    "PM1": 3.5,
    "PM2.5": 3.7,
    "PM4": 3.7,
    "PM10": 3.7,
    "HUM1": 40.51,
    "TMP1": 19.08,
    "VOC": 131,
    "NOX": 1,
    "CO2": 458,
    "HUM2": 38.75,
    "TMP2": 19,
    "HUM": 40.65,
    "TMP": 18.8
  },
  {
    "timestamp": "2026-01-20T09:23:25.000Z",
    "PM1": 3.8,
    "PM2.5": 3.9,
    "PM4": 3.9,
    "PM10": 3.9,
    "HUM1": 40.47,
    "TMP1": 19.08,
    "VOC": 132,
    "NOX": 1,
    "CO2": 459,
    "HUM2": 38.7,
    "TMP2": 19,
    "HUM": 40.63,
    "TMP": 18.81
  },
  {
    "timestamp": "2026-01-20T09:23:55.000Z",
    "PM1": 4.2,
    "PM2.5": 4.4,
    "PM4": 4.4,
    "PM10": 4.4,
    "HUM1": 40.48,
    "TMP1": 19.08,
    "VOC": 132,
    "NOX": 1,
    "CO2": 459,
    "HUM2": 38.75,
    "TMP2": 19,
    "HUM": 40.69,
    "TMP": 18.83
  },
  {
    "timestamp": "2026-01-20T09:24:25.000Z",
    "PM1": 3.4,
    "PM2.5": 3.6,
    "PM4": 3.6,
    "PM10": 3.6,
    "HUM1": 40.49,
    "TMP1": 19.08,
    "VOC": 132,
    "NOX": 1,
    "CO2": 459,
    "HUM2": 38.72,
    "TMP2": 19.01,
    "HUM": 40.64,
    "TMP": 18.82
  },
  {
    "timestamp": "2026-01-20T09:24:55.000Z",
    "PM1": 3.3,
    "PM2.5": 3.5,
    "PM4": 3.5,
    "PM10": 3.5,
    "HUM1": 40.4,
    "TMP1": 19.08,
    "VOC": 133,
    "NOX": 1,
    "CO2": 457,
    "HUM2": 38.74,
    "TMP2": 19,
    "HUM": 40.64,
    "TMP": 18.8
  },
  {
    "timestamp": "2026-01-20T09:25:25.000Z",
    "PM1": 3.5,
    "PM2.5": 3.7,
    "PM4": 3.7,
    "PM10": 3.7,
    "HUM1": 40.42,
    "TMP1": 19.08,
    "VOC": 132,
    "NOX": 1,
    "CO2": 458,
    "HUM2": 38.76,
    "TMP2": 18.99,
    "HUM": 40.68,
    "TMP": 18.8
  },
  {
    "timestamp": "2026-01-20T09:25:55.000Z",
    "PM1": 3.7,
    "PM2.5": 3.9,
    "PM4": 3.9,
    "PM10": 3.9,
    "HUM1": 40.46,
    "TMP1": 19.08,
    "VOC": 133,
    "NOX": 1,
    "CO2": 457,
    "HUM2": 38.76,
    "TMP2": 19,
    "HUM": 40.7,
    "TMP": 18.81
  },
  {
    "timestamp": "2026-01-20T09:26:25.000Z",
    "PM1": 3.7,
    "PM2.5": 3.8,
    "PM4": 3.8,
    "PM10": 3.8,
    "HUM1": 40.43,
    "TMP1": 19.08,
    "VOC": 133,
    "NOX": 1,
    "CO2": 456,
    "HUM2": 38.72,
    "TMP2": 18.98,
    "HUM": 40.66,
    "TMP": 18.83
  },
  {
    "timestamp": "2026-01-20T09:26:55.000Z",
    "PM1": 3.9,
    "PM2.5": 4.1,
    "PM4": 4.1,
    "PM10": 4.1,
    "HUM1": 40.43,
    "TMP1": 19.08,
    "VOC": 132,
    "NOX": 1,
    "CO2": 455,
    "HUM2": 38.75,
    "TMP2": 18.98,
    "HUM": 40.61,
    "TMP": 18.81
  },
  {
    "timestamp": "2026-01-20T09:27:24.000Z",
    "PM1": 4.2,
    "PM2.5": 4.4,
    "PM4": 4.4,
    "PM10": 4.4,
    "HUM1": 40.39,
    "TMP1": 19.08,
    "VOC": 133,
    "NOX": 1,
    "CO2": 454,
    "HUM2": 38.73,
    "TMP2": 18.99,
    "HUM": 40.55,
    "TMP": 18.79
  },
  {
    "timestamp": "2026-01-20T09:27:54.000Z",
    "PM1": 4.1,
    "PM2.5": 4.3,
    "PM4": 4.3,
    "PM10": 4.3,
    "HUM1": 40.39,
    "TMP1": 19.08,
    "VOC": 132,
    "NOX": 1,
    "CO2": 455,
    "HUM2": 38.66,
    "TMP2": 18.99,
    "HUM": 40.57,
    "TMP": 18.81
  },
  {
    "timestamp": "2026-01-20T09:28:24.000Z",
    "PM1": 3.4,
    "PM2.5": 3.6,
    "PM4": 3.6,
    "PM10": 3.6,
    "HUM1": 40.4,
    "TMP1": 19.08,
    "VOC": 133,
    "NOX": 1,
    "CO2": 456,
    "HUM2": 38.7,
    "TMP2": 19.01,
    "HUM": 40.6,
    "TMP": 18.8
  },
  {
    "timestamp": "2026-01-20T09:28:54.000Z",
    "PM1": 3.9,
    "PM2.5": 4.1,
    "PM4": 4.1,
    "PM10": 4.1,
    "HUM1": 40.34,
    "TMP1": 19.07,
    "VOC": 133,
    "NOX": 1,
    "CO2": 456,
    "HUM2": 38.69,
    "TMP2": 19,
    "HUM": 40.56,
    "TMP": 18.79
  },
  {
    "timestamp": "2026-01-20T09:29:24.000Z",
    "PM1": 3.6,
    "PM2.5": 3.8,
    "PM4": 3.8,
    "PM10": 3.8,
    "HUM1": 40.37,
    "TMP1": 19.07,
    "VOC": 133,
    "NOX": 1,
    "CO2": 455,
    "HUM2": 38.67,
    "TMP2": 18.97,
    "HUM": 40.57,
    "TMP": 18.78
  },
  {
    "timestamp": "2026-01-20T09:29:54.000Z",
    "PM1": 3.5,
    "PM2.5": 3.6,
    "PM4": 3.6,
    "PM10": 3.6,
    "HUM1": 40.41,
    "TMP1": 19.07,
    "VOC": 132,
    "NOX": 1,
    "CO2": 454,
    "HUM2": 38.65,
    "TMP2": 18.96,
    "HUM": 40.64,
    "TMP": 18.79
  },
  {
    "timestamp": "2026-01-20T09:30:24.000Z",
    "PM1": 3.3,
    "PM2.5": 3.4,
    "PM4": 3.4,
    "PM10": 3.4,
    "HUM1": 40.28,
    "TMP1": 19.07,
    "VOC": 131,
    "NOX": 1,
    "CO2": 454,
    "HUM2": 38.67,
    "TMP2": 18.95,
    "HUM": 40.6,
    "TMP": 18.79
  },
  {
    "timestamp": "2026-01-20T09:30:54.000Z",
    "PM1": 3.5,
    "PM2.5": 3.6,
    "PM4": 3.6,
    "PM10": 3.6,
    "HUM1": 40.27,
    "TMP1": 19.07,
    "VOC": 130,
    "NOX": 1,
    "CO2": 454,
    "HUM2": 38.67,
    "TMP2": 18.98,
    "HUM": 40.56,
    "TMP": 18.8
  },
  {
    "timestamp": "2026-01-20T09:31:24.000Z",
    "PM1": 3.4,
    "PM2.5": 3.6,
    "PM4": 3.6,
    "PM10": 3.6,
    "HUM1": 40.25,
    "TMP1": 19.06,
    "VOC": 129,
    "NOX": 1,
    "CO2": 454,
    "HUM2": 38.68,
    "TMP2": 18.96,
    "HUM": 40.61,
    "TMP": 18.77
  },
  {
    "timestamp": "2026-01-20T09:31:54.000Z",
    "PM1": 3.5,
    "PM2.5": 3.7,
    "PM4": 3.7,
    "PM10": 3.7,
    "HUM1": 40.43,
    "TMP1": 19.06,
    "VOC": 129,
    "NOX": 1,
    "CO2": 453,
    "HUM2": 38.64,
    "TMP2": 18.97,
    "HUM": 40.54,
    "TMP": 18.8
  },
  {
    "timestamp": "2026-01-20T09:32:24.000Z",
    "PM1": 3.8,
    "PM2.5": 3.9,
    "PM4": 3.9,
    "PM10": 3.9,
    "HUM1": 40.39,
    "TMP1": 19.06,
    "VOC": 128,
    "NOX": 1,
    "CO2": 454,
    "HUM2": 38.62,
    "TMP2": 18.96,
    "HUM": 40.56,
    "TMP": 18.77
  },
  {
    "timestamp": "2026-01-20T09:32:54.000Z",
    "PM1": 3.1,
    "PM2.5": 3.3,
    "PM4": 3.3,
    "PM10": 3.3,
    "HUM1": 40.27,
    "TMP1": 19.06,
    "VOC": 127,
    "NOX": 1,
    "CO2": 456,
    "HUM2": 38.66,
    "TMP2": 18.96,
    "HUM": 40.51,
    "TMP": 18.78
  },
  {
    "timestamp": "2026-01-20T09:33:24.000Z",
    "PM1": 2.9,
    "PM2.5": 3.1,
    "PM4": 3.1,
    "PM10": 3.1,
    "HUM1": 40.21,
    "TMP1": 19.06,
    "VOC": 126,
    "NOX": 1,
    "CO2": 456,
    "HUM2": 38.68,
    "TMP2": 18.96,
    "HUM": 40.53,
    "TMP": 18.76
  },
  {
    "timestamp": "2026-01-20T09:33:54.000Z",
    "PM1": 3.6,
    "PM2.5": 3.7,
    "PM4": 3.7,
    "PM10": 3.7,
    "HUM1": 40.21,
    "TMP1": 19.06,
    "VOC": 125,
    "NOX": 1,
    "CO2": 457,
    "HUM2": 38.64,
    "TMP2": 18.95,
    "HUM": 40.56,
    "TMP": 18.77
  },
  {
    "timestamp": "2026-01-20T09:34:24.000Z",
    "PM1": 3.1,
    "PM2.5": 3.3,
    "PM4": 3.3,
    "PM10": 3.3,
    "HUM1": 40.19,
    "TMP1": 19.06,
    "VOC": 122,
    "NOX": 1,
    "CO2": 457,
    "HUM2": 38.62,
    "TMP2": 18.96,
    "HUM": 40.53,
    "TMP": 18.76
  },
  {
    "timestamp": "2026-01-20T09:34:54.000Z",
    "PM1": 3.3,
    "PM2.5": 3.5,
    "PM4": 3.5,
    "PM10": 3.5,
    "HUM1": 40.15,
    "TMP1": 19.06,
    "VOC": 121,
    "NOX": 1,
    "CO2": 458,
    "HUM2": 38.64,
    "TMP2": 18.95,
    "HUM": 40.49,
    "TMP": 18.76
  },
  {
    "timestamp": "2026-01-20T09:35:24.000Z",
    "PM1": 3.7,
    "PM2.5": 3.9,
    "PM4": 3.9,
    "PM10": 3.9,
    "HUM1": 40.15,
    "TMP1": 19.06,
    "VOC": 118,
    "NOX": 1,
    "CO2": 457,
    "HUM2": 38.65,
    "TMP2": 18.95,
    "HUM": 40.67,
    "TMP": 18.77
  },
  {
    "timestamp": "2026-01-20T09:35:54.000Z",
    "PM1": 4.2,
    "PM2.5": 4.4,
    "PM4": 4.4,
    "PM10": 4.4,
    "HUM1": 40.19,
    "TMP1": 19.06,
    "VOC": 118,
    "NOX": 1,
    "CO2": 457,
    "HUM2": 38.7,
    "TMP2": 18.93,
    "HUM": 40.53,
    "TMP": 18.76
  },
  {
    "timestamp": "2026-01-20T09:36:24.000Z",
    "PM1": 3.6,
    "PM2.5": 3.8,
    "PM4": 3.8,
    "PM10": 3.8,
    "HUM1": 40.09,
    "TMP1": 19.06,
    "VOC": 117,
    "NOX": 1,
    "CO2": 455,
    "HUM2": 38.65,
    "TMP2": 18.95,
    "HUM": 40.47,
    "TMP": 18.76
  }
]